<?xml version="1.0" encoding="UTF-8" standalone="yes"?><w:document xmlns:mc="http://schemas.openxmlformats.org/markup-compatibility/2006" xmlns:o="urn:schemas-microsoft-com:office:office" xmlns:r="http://schemas.openxmlformats.org/officeDocument/2006/relationships" xmlns:m="http://schemas.openxmlformats.org/officeDocument/2006/math" xmlns:v="urn:schemas-microsoft-com:vml" xmlns:wp="http://schemas.openxmlformats.org/drawingml/2006/wordprocessingDrawing" xmlns:w10="urn:schemas-microsoft-com:office:word" xmlns:w="http://schemas.openxmlformats.org/wordprocessingml/2006/main" xmlns:wne="http://schemas.microsoft.com/office/word/2006/wordml" xmlns:sl="http://schemas.openxmlformats.org/schemaLibrary/2006/main" xmlns:a="http://schemas.openxmlformats.org/drawingml/2006/main" xmlns:pic="http://schemas.openxmlformats.org/drawingml/2006/picture" xmlns:c="http://schemas.openxmlformats.org/drawingml/2006/chart" xmlns:lc="http://schemas.openxmlformats.org/drawingml/2006/lockedCanvas" xmlns:dgm="http://schemas.openxmlformats.org/drawingml/2006/diagram" xmlns:wps="http://schemas.microsoft.com/office/word/2010/wordprocessingShape" xmlns:wpg="http://schemas.microsoft.com/office/word/2010/wordprocessingGroup" xmlns:w14="http://schemas.microsoft.com/office/word/2010/wordml" xmlns:w15="http://schemas.microsoft.com/office/word/2012/wordml" xmlns:w16="http://schemas.microsoft.com/office/word/2018/wordml" xmlns:w16cex="http://schemas.microsoft.com/office/word/2018/wordml/cex" xmlns:w16cid="http://schemas.microsoft.com/office/word/2016/wordml/cid" xmlns="http://schemas.microsoft.com/office/tasks/2019/documenttasks" xmlns:cr="http://schemas.microsoft.com/office/comments/2020/reactions"><w:body><w:p w:rsidR="00000000" w:rsidDel="00000000" w:rsidP="00000000" w:rsidRDefault="00000000" w:rsidRPr="00000000" w14:paraId="00000001"><w:pPr><w:pBdr><w:top w:space="0" w:sz="0" w:val="nil"/><w:left w:space="0" w:sz="0" w:val="nil"/><w:bottom w:space="0" w:sz="0" w:val="nil"/><w:right w:space="0" w:sz="0" w:val="nil"/><w:between w:space="0" w:sz="0" w:val="nil"/></w:pBdr><w:shd w:fill="auto" w:val="clear"/><w:spacing w:after="240" w:line="275.9999942779541" w:lineRule="auto"/><w:rPr><w:rFonts w:ascii="Google Sans" w:cs="Google Sans" w:eastAsia="Google Sans" w:hAnsi="Google Sans"/><w:color w:val="1f1f1f"/></w:rPr></w:pPr><w:r w:rsidDel="00000000" w:rsidR="00000000" w:rsidRPr="00000000"><w:rPr><w:rFonts w:ascii="Google Sans" w:cs="Google Sans" w:eastAsia="Google Sans" w:hAnsi="Google Sans"/><w:color w:val="1f1f1f"/><w:rtl w:val="0"/></w:rPr><w:t xml:space="preserve">Got it. We are staying purely on the Frontend. We are building the </w:t></w:r><w:r w:rsidDel="00000000" w:rsidR="00000000" w:rsidRPr="00000000"><w:rPr><w:rFonts w:ascii="Google Sans" w:cs="Google Sans" w:eastAsia="Google Sans" w:hAnsi="Google Sans"/><w:b w:val="1"/><w:bCs w:val="1"/><w:color w:val="1f1f1f"/><w:rtl w:val="0"/></w:rPr><w:t xml:space="preserve">VTT Player Interface</w:t></w:r><w:r w:rsidDel="00000000" w:rsidR="00000000" w:rsidRPr="00000000"><w:rPr><w:rFonts w:ascii="Google Sans" w:cs="Google Sans" w:eastAsia="Google Sans" w:hAnsi="Google Sans"/><w:color w:val="1f1f1f"/><w:rtl w:val="0"/></w:rPr><w:t xml:space="preserve"> as its own completely standalone, pristine application.</w:t></w:r></w:p><w:p w:rsidR="00000000" w:rsidDel="00000000" w:rsidP="00000000" w:rsidRDefault="00000000" w:rsidRPr="00000000" w14:paraId="00000002"><w:pPr><w:pBdr><w:top w:space="0" w:sz="0" w:val="nil"/><w:left w:space="0" w:sz="0" w:val="nil"/><w:bottom w:space="0" w:sz="0" w:val="nil"/><w:right w:space="0" w:sz="0" w:val="nil"/><w:between w:space="0" w:sz="0" w:val="nil"/></w:pBdr><w:shd w:fill="auto" w:val="clear"/><w:spacing w:after="240" w:line="275.9999942779541" w:lineRule="auto"/><w:rPr><w:rFonts w:ascii="Google Sans" w:cs="Google Sans" w:eastAsia="Google Sans" w:hAnsi="Google Sans"/><w:color w:val="1f1f1f"/></w:rPr></w:pPr><w:r w:rsidDel="00000000" w:rsidR="00000000" w:rsidRPr="00000000"><w:rPr><w:rFonts w:ascii="Google Sans" w:cs="Google Sans" w:eastAsia="Google Sans" w:hAnsi="Google Sans"/><w:color w:val="1f1f1f"/><w:rtl w:val="0"/></w:rPr><w:t xml:space="preserve">This React app will contain </w:t></w:r><w:r w:rsidDel="00000000" w:rsidR="00000000" w:rsidRPr="00000000"><w:rPr><w:rFonts w:ascii="Google Sans" w:cs="Google Sans" w:eastAsia="Google Sans" w:hAnsi="Google Sans"/><w:b w:val="1"/><w:bCs w:val="1"/><w:color w:val="1f1f1f"/><w:rtl w:val="0"/></w:rPr><w:t xml:space="preserve">zero game logic</w:t></w:r><w:r w:rsidDel="00000000" w:rsidR="00000000" w:rsidRPr="00000000"><w:rPr><w:rFonts w:ascii="Google Sans" w:cs="Google Sans" w:eastAsia="Google Sans" w:hAnsi="Google Sans"/><w:color w:val="1f1f1f"/><w:rtl w:val="0"/></w:rPr><w:t xml:space="preserve">. It is strictly a beautiful, interactive &quot;dumb terminal.&quot; It renders your 2D tiles, draws your stamina bars, captures your mouse clicks, and sends them as JSON payloads to whatever backend you eventually plug it into.</w:t></w:r></w:p><w:p w:rsidR="00000000" w:rsidDel="00000000" w:rsidP="00000000" w:rsidRDefault="00000000" w:rsidRPr="00000000" w14:paraId="00000003"><w:pPr><w:pBdr><w:top w:space="0" w:sz="0" w:val="nil"/><w:left w:space="0" w:sz="0" w:val="nil"/><w:bottom w:space="0" w:sz="0" w:val="nil"/><w:right w:space="0" w:sz="0" w:val="nil"/><w:between w:space="0" w:sz="0" w:val="nil"/></w:pBdr><w:shd w:fill="auto" w:val="clear"/><w:spacing w:after="240" w:line="275.9999942779541" w:lineRule="auto"/><w:rPr><w:rFonts w:ascii="Google Sans" w:cs="Google Sans" w:eastAsia="Google Sans" w:hAnsi="Google Sans"/><w:color w:val="1f1f1f"/></w:rPr></w:pPr><w:r w:rsidDel="00000000" w:rsidR="00000000" w:rsidRPr="00000000"><w:rPr><w:rFonts w:ascii="Google Sans" w:cs="Google Sans" w:eastAsia="Google Sans" w:hAnsi="Google Sans"/><w:color w:val="1f1f1f"/><w:rtl w:val="0"/></w:rPr><w:t xml:space="preserve">If you are starting fresh, ditch the old auto-coder repository completely. Create a new React project (e.g., saga_vtt_client). Here is the exact, developer-ready blueprint to build the 5-panel layout we discussed.</w:t></w:r></w:p><w:p w:rsidR="00000000" w:rsidDel="00000000" w:rsidP="00000000" w:rsidRDefault="00000000" w:rsidRPr="00000000" w14:paraId="00000004"><w:pPr><w:pStyle w:val="Heading1"/><w:pBdr><w:top w:space="0" w:sz="0" w:val="nil"/><w:left w:space="0" w:sz="0" w:val="nil"/><w:bottom w:space="0" w:sz="0" w:val="nil"/><w:right w:space="0" w:sz="0" w:val="nil"/><w:between w:space="0" w:sz="0" w:val="nil"/></w:pBdr><w:shd w:fill="auto" w:val="clear"/><w:spacing w:after="120" w:before="120" w:line="275.9999942779541" w:lineRule="auto"/><w:rPr><w:rFonts w:ascii="Google Sans" w:cs="Google Sans" w:eastAsia="Google Sans" w:hAnsi="Google Sans"/><w:color w:val="1f1f1f"/></w:rPr></w:pPr><w:r w:rsidDel="00000000" w:rsidR="00000000" w:rsidRPr="00000000"><w:pict><v:rect style="width:0.0pt;height:1.5pt" o:hr="t" o:hrstd="t" o:hralign="center" fillcolor="#A0A0A0" stroked="f"/></w:pict></w:r><w:r w:rsidDel="00000000" w:rsidR="00000000" w:rsidRPr="00000000"><w:rPr><w:rFonts w:ascii="Google Sans" w:cs="Google Sans" w:eastAsia="Google Sans" w:hAnsi="Google Sans"/><w:color w:val="1f1f1f"/><w:rtl w:val="0"/></w:rPr><w:t xml:space="preserve">🎨 S.A.G.A. VTT BLUEPRINT: The Player Interface</w:t></w:r></w:p><w:p w:rsidR="00000000" w:rsidDel="00000000" w:rsidP="00000000" w:rsidRDefault="00000000" w:rsidRPr="00000000" w14:paraId="00000005"><w:pPr><w:pStyle w:val="Heading2"/><w:pBdr><w:top w:space="0" w:sz="0" w:val="nil"/><w:left w:space="0" w:sz="0" w:val="nil"/><w:bottom w:space="0" w:sz="0" w:val="nil"/><w:right w:space="0" w:sz="0" w:val="nil"/><w:between w:space="0" w:sz="0" w:val="nil"/></w:pBdr><w:shd w:fill="auto" w:val="clear"/><w:spacing w:after="120" w:before="0" w:line="275.9999942779541" w:lineRule="auto"/><w:rPr><w:rFonts w:ascii="Google Sans" w:cs="Google Sans" w:eastAsia="Google Sans" w:hAnsi="Google Sans"/><w:color w:val="1f1f1f"/></w:rPr></w:pPr><w:r w:rsidDel="00000000" w:rsidR="00000000" w:rsidRPr="00000000"><w:rPr><w:rFonts w:ascii="Google Sans" w:cs="Google Sans" w:eastAsia="Google Sans" w:hAnsi="Google Sans"/><w:color w:val="1f1f1f"/><w:rtl w:val="0"/></w:rPr><w:t xml:space="preserve">1. Directory Structure</w:t></w:r></w:p><w:p w:rsidR="00000000" w:rsidDel="00000000" w:rsidP="00000000" w:rsidRDefault="00000000" w:rsidRPr="00000000" w14:paraId="00000006"><w:pPr><w:pBdr><w:top w:space="0" w:sz="0" w:val="nil"/><w:left w:space="0" w:sz="0" w:val="nil"/><w:bottom w:space="0" w:sz="0" w:val="nil"/><w:right w:space="0" w:sz="0" w:val="nil"/><w:between w:space="0" w:sz="0" w:val="nil"/></w:pBdr><w:shd w:fill="auto" w:val="clear"/><w:spacing w:after="240" w:line="275.9999942779541" w:lineRule="auto"/><w:rPr><w:rFonts w:ascii="Google Sans" w:cs="Google Sans" w:eastAsia="Google Sans" w:hAnsi="Google Sans"/><w:color w:val="1f1f1f"/></w:rPr></w:pPr><w:r w:rsidDel="00000000" w:rsidR="00000000" w:rsidRPr="00000000"><w:rPr><w:rFonts w:ascii="Google Sans" w:cs="Google Sans" w:eastAsia="Google Sans" w:hAnsi="Google Sans"/><w:color w:val="1f1f1f"/><w:rtl w:val="0"/></w:rPr><w:t xml:space="preserve">Keep your components strictly organized by the visual zones of the screen.</w:t></w:r></w:p><w:p w:rsidR="00000000" w:rsidDel="00000000" w:rsidP="00000000" w:rsidRDefault="00000000" w:rsidRPr="00000000" w14:paraId="00000007"><w:pPr><w:pBdr><w:top w:space="0" w:sz="0" w:val="nil"/><w:left w:space="0" w:sz="0" w:val="nil"/><w:bottom w:space="0" w:sz="0" w:val="nil"/><w:right w:space="0" w:sz="0" w:val="nil"/><w:between w:space="0" w:sz="0" w:val="nil"/></w:pBdr><w:shd w:fill="auto" w:val="clear"/><w:spacing w:after="240" w:line="275.9999942779541" w:lineRule="auto"/><w:ind w:left="240" w:right="120" w:firstLine="0"/><w:rPr><w:rFonts w:ascii="Google Sans" w:cs="Google Sans" w:eastAsia="Google Sans" w:hAnsi="Google Sans"/><w:color w:val="1f1f1f"/></w:rPr></w:pPr><w:r w:rsidDel="00000000" w:rsidR="00000000" w:rsidRPr="00000000"><w:rPr><w:rtl w:val="0"/></w:rPr></w:r></w:p><w:p w:rsidR="00000000" w:rsidDel="00000000" w:rsidP="00000000" w:rsidRDefault="00000000" w:rsidRPr="00000000" w14:paraId="00000008"><w:pPr><w:pBdr><w:top w:space="0" w:sz="0" w:val="nil"/><w:left w:space="0" w:sz="0" w:val="nil"/><w:bottom w:space="0" w:sz="0" w:val="nil"/><w:right w:space="0" w:sz="0" w:val="nil"/><w:between w:space="0" w:sz="0" w:val="nil"/></w:pBdr><w:shd w:fill="auto" w:val="clear"/><w:spacing w:after="150" w:before="120" w:line="275.9999942779541" w:lineRule="auto"/><w:ind w:left="240" w:right="120" w:firstLine="0"/><w:rPr><w:rFonts w:ascii="Google Sans" w:cs="Google Sans" w:eastAsia="Google Sans" w:hAnsi="Google Sans"/><w:color w:val="444746"/><w:shd w:fill="f0f4f9" w:val="clear"/></w:rPr></w:pPr><w:r w:rsidDel="00000000" w:rsidR="00000000" w:rsidRPr="00000000"><w:rPr><w:rFonts w:ascii="Google Sans" w:cs="Google Sans" w:eastAsia="Google Sans" w:hAnsi="Google Sans"/><w:color w:val="444746"/><w:shd w:fill="f0f4f9" w:val="clear"/><w:rtl w:val="0"/></w:rPr><w:t xml:space="preserve">Plaintext</w:t></w:r></w:p><w:p w:rsidR="00000000" w:rsidDel="00000000" w:rsidP="00000000" w:rsidRDefault="00000000" w:rsidRPr="00000000" w14:paraId="00000009"><w:pPr><w:pBdr><w:top w:space="0" w:sz="0" w:val="nil"/><w:left w:space="0" w:sz="0" w:val="nil"/><w:bottom w:space="0" w:sz="0" w:val="nil"/><w:right w:space="0" w:sz="0" w:val="nil"/><w:between w:space="0" w:sz="0" w:val="nil"/></w:pBdr><w:shd w:fill="auto" w:val="clear"/><w:spacing w:line="275.9999942779541" w:lineRule="auto"/><w:rPr><w:rFonts w:ascii="Google Sans" w:cs="Google Sans" w:eastAsia="Google Sans" w:hAnsi="Google Sans"/><w:color w:val="444746"/><w:shd w:fill="f0f4f9" w:val="clear"/></w:rPr></w:pPr><w:r w:rsidDel="00000000" w:rsidR="00000000" w:rsidRPr="00000000"><w:rPr><w:rtl w:val="0"/></w:rPr></w:r></w:p><w:p w:rsidR="00000000" w:rsidDel="00000000" w:rsidP="00000000" w:rsidRDefault="00000000" w:rsidRPr="00000000" w14:paraId="0000000A"><w:pPr><w:pBdr><w:top w:space="0" w:sz="0" w:val="nil"/><w:left w:space="0" w:sz="0" w:val="nil"/><w:bottom w:space="0" w:sz="0" w:val="nil"/><w:right w:space="0" w:sz="0" w:val="nil"/><w:between w:space="0" w:sz="0" w:val="nil"/></w:pBdr><w:shd w:fill="auto" w:val="clear"/><w:spacing w:line="275.9999942779541" w:lineRule="auto"/><w:rPr><w:rFonts w:ascii="Google Sans" w:cs="Google Sans" w:eastAsia="Google Sans" w:hAnsi="Google Sans"/><w:color w:val="444746"/><w:shd w:fill="f0f4f9" w:val="clear"/></w:rPr></w:pPr><w:r w:rsidDel="00000000" w:rsidR="00000000" w:rsidRPr="00000000"><w:rPr><w:rtl w:val="0"/></w:rPr></w:r></w:p><w:p w:rsidR="00000000" w:rsidDel="00000000" w:rsidP="00000000" w:rsidRDefault="00000000" w:rsidRPr="00000000" w14:paraId="0000000B"><w:pPr><w:pBdr><w:top w:space="0" w:sz="0" w:val="nil"/><w:left w:space="0" w:sz="0" w:val="nil"/><w:bottom w:space="0" w:sz="0" w:val="nil"/><w:right w:space="0" w:sz="0" w:val="nil"/><w:between w:space="0" w:sz="0" w:val="nil"/></w:pBdr><w:shd w:fill="auto" w:val="clear"/><w:spacing w:line="275.9999942779541" w:lineRule="auto"/><w:rPr><w:rFonts w:ascii="Google Sans" w:cs="Google Sans" w:eastAsia="Google Sans" w:hAnsi="Google Sans"/><w:color w:val="1f1f1f"/><w:shd w:fill="f0f4f9" w:val="clear"/></w:rPr></w:pPr><w:r w:rsidDel="00000000" w:rsidR="00000000" w:rsidRPr="00000000"><w:rPr><w:rFonts w:ascii="Google Sans" w:cs="Google Sans" w:eastAsia="Google Sans" w:hAnsi="Google Sans"/><w:color w:val="1f1f1f"/><w:shd w:fill="f0f4f9" w:val="clear"/><w:rtl w:val="0"/></w:rPr><w:t xml:space="preserve">saga_vtt_client/</w:t><w:br w:type="textWrapping"/><w:t xml:space="preserve">│</w:t><w:br w:type="textWrapping"/><w:t xml:space="preserve">├── package.json (React + Tailwind CSS + Pixi.js)</w:t><w:br w:type="textWrapping"/><w:t xml:space="preserve">├── src/</w:t><w:br w:type="textWrapping"/><w:t xml:space="preserve">│   ├── App.tsx                  # The Master Grid Layout</w:t><w:br w:type="textWrapping"/><w:t xml:space="preserve">│   ├── store/</w:t><w:br w:type="textWrapping"/><w:t xml:space="preserve">│   │   └── useGameStore.ts      # Zustand (or Context) to hold the JSON state</w:t><w:br w:type="textWrapping"/><w:t xml:space="preserve">│   ├── components/</w:t><w:br w:type="textWrapping"/><w:t xml:space="preserve">│   │   ├── map/</w:t><w:br w:type="textWrapping"/><w:t xml:space="preserve">│   │   │   └── PixiBattlemap.tsx # Center Stage (70% of screen)</w:t><w:br w:type="textWrapping"/><w:t xml:space="preserve">│   │   ├── left_panel/</w:t><w:br w:type="textWrapping"/><w:t xml:space="preserve">│   │   │   └── DirectorLog.tsx  # The AI Chat &amp; Math Feed</w:t><w:br w:type="textWrapping"/><w:t xml:space="preserve">│   │   ├── bottom_console/</w:t><w:br w:type="textWrapping"/><w:t xml:space="preserve">│   │   │   ├── ActionDeck.tsx   # Skill buttons &amp; Quick Inventory</w:t><w:br w:type="textWrapping"/><w:t xml:space="preserve">│   │   │   └── ResourceOrbs.tsx # Stamina / Focus bars &amp; Burn Slider</w:t><w:br w:type="textWrapping"/><w:t xml:space="preserve">│   │   ├── right_panel/</w:t><w:br w:type="textWrapping"/><w:t xml:space="preserve">│   │   │   ├── BioMatrix.tsx    # 12 Stats &amp; Scars/Stars pips</w:t><w:br w:type="textWrapping"/><w:t xml:space="preserve">│   │   │   └── InjurySlots.tsx  # Dual-Track Body/Mind visualizer</w:t><w:br w:type="textWrapping"/><w:t xml:space="preserve">│   │   └── hud/</w:t><w:br w:type="textWrapping"/><w:t xml:space="preserve">│   │       └── QuestTracker.tsx # Top Right checklist</w:t><w:br w:type="textWrapping"/></w:r></w:p><w:p w:rsidR="00000000" w:rsidDel="00000000" w:rsidP="00000000" w:rsidRDefault="00000000" w:rsidRPr="00000000" w14:paraId="0000000C"><w:pPr><w:pStyle w:val="Heading2"/><w:pBdr><w:top w:space="0" w:sz="0" w:val="nil"/><w:left w:space="0" w:sz="0" w:val="nil"/><w:bottom w:space="0" w:sz="0" w:val="nil"/><w:right w:space="0" w:sz="0" w:val="nil"/><w:between w:space="0" w:sz="0" w:val="nil"/></w:pBdr><w:shd w:fill="auto" w:val="clear"/><w:spacing w:after="120" w:before="120" w:line="275.9999942779541" w:lineRule="auto"/><w:rPr><w:rFonts w:ascii="Google Sans" w:cs="Google Sans" w:eastAsia="Google Sans" w:hAnsi="Google Sans"/><w:color w:val="1f1f1f"/></w:rPr></w:pPr><w:r w:rsidDel="00000000" w:rsidR="00000000" w:rsidRPr="00000000"><w:pict><v:rect style="width:0.0pt;height:1.5pt" o:hr="t" o:hrstd="t" o:hralign="center" fillcolor="#A0A0A0" stroked="f"/></w:pict></w:r><w:r w:rsidDel="00000000" w:rsidR="00000000" w:rsidRPr="00000000"><w:rPr><w:rFonts w:ascii="Google Sans" w:cs="Google Sans" w:eastAsia="Google Sans" w:hAnsi="Google Sans"/><w:color w:val="1f1f1f"/><w:rtl w:val="0"/></w:rPr><w:t xml:space="preserve">2. The Master Layout (App.tsx)</w:t></w:r></w:p><w:p w:rsidR="00000000" w:rsidDel="00000000" w:rsidP="00000000" w:rsidRDefault="00000000" w:rsidRPr="00000000" w14:paraId="0000000D"><w:pPr><w:pBdr><w:top w:space="0" w:sz="0" w:val="nil"/><w:left w:space="0" w:sz="0" w:val="nil"/><w:bottom w:space="0" w:sz="0" w:val="nil"/><w:right w:space="0" w:sz="0" w:val="nil"/><w:between w:space="0" w:sz="0" w:val="nil"/></w:pBdr><w:shd w:fill="auto" w:val="clear"/><w:spacing w:after="240" w:line="275.9999942779541" w:lineRule="auto"/><w:rPr><w:rFonts w:ascii="Google Sans" w:cs="Google Sans" w:eastAsia="Google Sans" w:hAnsi="Google Sans"/><w:color w:val="1f1f1f"/></w:rPr></w:pPr><w:r w:rsidDel="00000000" w:rsidR="00000000" w:rsidRPr="00000000"><w:rPr><w:rFonts w:ascii="Google Sans" w:cs="Google Sans" w:eastAsia="Google Sans" w:hAnsi="Google Sans"/><w:color w:val="1f1f1f"/><w:rtl w:val="0"/></w:rPr><w:t xml:space="preserve">We use </w:t></w:r><w:r w:rsidDel="00000000" w:rsidR="00000000" w:rsidRPr="00000000"><w:rPr><w:rFonts w:ascii="Google Sans" w:cs="Google Sans" w:eastAsia="Google Sans" w:hAnsi="Google Sans"/><w:b w:val="1"/><w:bCs w:val="1"/><w:color w:val="1f1f1f"/><w:rtl w:val="0"/></w:rPr><w:t xml:space="preserve">Tailwind CSS CSS Grid</w:t></w:r><w:r w:rsidDel="00000000" w:rsidR="00000000" w:rsidRPr="00000000"><w:rPr><w:rFonts w:ascii="Google Sans" w:cs="Google Sans" w:eastAsia="Google Sans" w:hAnsi="Google Sans"/><w:color w:val="1f1f1f"/><w:rtl w:val="0"/></w:rPr><w:t xml:space="preserve"> to lock the interface into a fullscreen, non-scrolling &quot;Video Game&quot; layout. No gross scrollbars. Everything is fixed to the screen edges.</w:t></w:r></w:p><w:p w:rsidR="00000000" w:rsidDel="00000000" w:rsidP="00000000" w:rsidRDefault="00000000" w:rsidRPr="00000000" w14:paraId="0000000E"><w:pPr><w:pBdr><w:top w:space="0" w:sz="0" w:val="nil"/><w:left w:space="0" w:sz="0" w:val="nil"/><w:bottom w:space="0" w:sz="0" w:val="nil"/><w:right w:space="0" w:sz="0" w:val="nil"/><w:between w:space="0" w:sz="0" w:val="nil"/></w:pBdr><w:shd w:fill="auto" w:val="clear"/><w:spacing w:after="240" w:line="275.9999942779541" w:lineRule="auto"/><w:ind w:left="240" w:right="120" w:firstLine="0"/><w:rPr><w:rFonts w:ascii="Google Sans" w:cs="Google Sans" w:eastAsia="Google Sans" w:hAnsi="Google Sans"/><w:color w:val="1f1f1f"/></w:rPr></w:pPr><w:r w:rsidDel="00000000" w:rsidR="00000000" w:rsidRPr="00000000"><w:rPr><w:rtl w:val="0"/></w:rPr></w:r></w:p><w:p w:rsidR="00000000" w:rsidDel="00000000" w:rsidP="00000000" w:rsidRDefault="00000000" w:rsidRPr="00000000" w14:paraId="0000000F"><w:pPr><w:pBdr><w:top w:space="0" w:sz="0" w:val="nil"/><w:left w:space="0" w:sz="0" w:val="nil"/><w:bottom w:space="0" w:sz="0" w:val="nil"/><w:right w:space="0" w:sz="0" w:val="nil"/><w:between w:space="0" w:sz="0" w:val="nil"/></w:pBdr><w:shd w:fill="auto" w:val="clear"/><w:spacing w:after="150" w:before="120" w:line="275.9999942779541" w:lineRule="auto"/><w:ind w:left="240" w:right="120" w:firstLine="0"/><w:rPr><w:rFonts w:ascii="Google Sans" w:cs="Google Sans" w:eastAsia="Google Sans" w:hAnsi="Google Sans"/><w:color w:val="444746"/><w:shd w:fill="f0f4f9" w:val="clear"/></w:rPr></w:pPr><w:r w:rsidDel="00000000" w:rsidR="00000000" w:rsidRPr="00000000"><w:rPr><w:rFonts w:ascii="Google Sans" w:cs="Google Sans" w:eastAsia="Google Sans" w:hAnsi="Google Sans"/><w:color w:val="444746"/><w:shd w:fill="f0f4f9" w:val="clear"/><w:rtl w:val="0"/></w:rPr><w:t xml:space="preserve">TypeScript</w:t></w:r></w:p><w:p w:rsidR="00000000" w:rsidDel="00000000" w:rsidP="00000000" w:rsidRDefault="00000000" w:rsidRPr="00000000" w14:paraId="00000010"><w:pPr><w:pBdr><w:top w:space="0" w:sz="0" w:val="nil"/><w:left w:space="0" w:sz="0" w:val="nil"/><w:bottom w:space="0" w:sz="0" w:val="nil"/><w:right w:space="0" w:sz="0" w:val="nil"/><w:between w:space="0" w:sz="0" w:val="nil"/></w:pBdr><w:shd w:fill="auto" w:val="clear"/><w:spacing w:line="275.9999942779541" w:lineRule="auto"/><w:rPr><w:rFonts w:ascii="Google Sans" w:cs="Google Sans" w:eastAsia="Google Sans" w:hAnsi="Google Sans"/><w:color w:val="444746"/><w:shd w:fill="f0f4f9" w:val="clear"/></w:rPr></w:pPr><w:r w:rsidDel="00000000" w:rsidR="00000000" w:rsidRPr="00000000"><w:rPr><w:rtl w:val="0"/></w:rPr></w:r></w:p><w:p w:rsidR="00000000" w:rsidDel="00000000" w:rsidP="00000000" w:rsidRDefault="00000000" w:rsidRPr="00000000" w14:paraId="00000011"><w:pPr><w:pBdr><w:top w:space="0" w:sz="0" w:val="nil"/><w:left w:space="0" w:sz="0" w:val="nil"/><w:bottom w:space="0" w:sz="0" w:val="nil"/><w:right w:space="0" w:sz="0" w:val="nil"/><w:between w:space="0" w:sz="0" w:val="nil"/></w:pBdr><w:shd w:fill="auto" w:val="clear"/><w:spacing w:line="275.9999942779541" w:lineRule="auto"/><w:rPr><w:rFonts w:ascii="Google Sans" w:cs="Google Sans" w:eastAsia="Google Sans" w:hAnsi="Google Sans"/><w:color w:val="444746"/><w:shd w:fill="f0f4f9" w:val="clear"/></w:rPr></w:pPr><w:r w:rsidDel="00000000" w:rsidR="00000000" w:rsidRPr="00000000"><w:rPr><w:rtl w:val="0"/></w:rPr></w:r></w:p><w:p w:rsidR="00000000" w:rsidDel="00000000" w:rsidP="00000000" w:rsidRDefault="00000000" w:rsidRPr="00000000" w14:paraId="00000012"><w:pPr><w:pBdr><w:top w:space="0" w:sz="0" w:val="nil"/><w:left w:space="0" w:sz="0" w:val="nil"/><w:bottom w:space="0" w:sz="0" w:val="nil"/><w:right w:space="0" w:sz="0" w:val="nil"/><w:between w:space="0" w:sz="0" w:val="nil"/></w:pBdr><w:shd w:fill="auto" w:val="clear"/><w:spacing w:line="275.9999942779541" w:lineRule="auto"/><w:rPr><w:rFonts w:ascii="Google Sans" w:cs="Google Sans" w:eastAsia="Google Sans" w:hAnsi="Google Sans"/><w:color w:val="1f1f1f"/><w:shd w:fill="f0f4f9" w:val="clear"/></w:rPr></w:pPr><w:r w:rsidDel="00000000" w:rsidR="00000000" w:rsidRPr="00000000"><w:rPr><w:rFonts w:ascii="Google Sans" w:cs="Google Sans" w:eastAsia="Google Sans" w:hAnsi="Google Sans"/><w:color w:val="1f1f1f"/><w:shd w:fill="f0f4f9" w:val="clear"/><w:rtl w:val="0"/></w:rPr><w:t xml:space="preserve">import React, { useState } from 'react';</w:t><w:br w:type="textWrapping"/><w:t xml:space="preserve">import { PixiBattlemap } from './components/map/PixiBattlemap';</w:t><w:br w:type="textWrapping"/><w:t xml:space="preserve">import { DirectorLog } from './components/left_panel/DirectorLog';</w:t><w:br w:type="textWrapping"/><w:t xml:space="preserve">import { ActionDeck } from './components/bottom_console/ActionDeck';</w:t><w:br w:type="textWrapping"/><w:t xml:space="preserve">import { BioMatrix } from './components/right_panel/BioMatrix';</w:t><w:br w:type="textWrapping"/><w:t xml:space="preserve">import { QuestTracker } from './components/hud/QuestTracker';</w:t><w:br w:type="textWrapping"/><w:br w:type="textWrapping"/><w:t xml:space="preserve">export default function App() {</w:t><w:br w:type="textWrapping"/><w:t xml:space="preserve">  const [isBioMatrixOpen, setBioMatrixOpen] = useState(false);</w:t><w:br w:type="textWrapping"/><w:br w:type="textWrapping"/><w:t xml:space="preserve">  return (</w:t><w:br w:type="textWrapping"/><w:t xml:space="preserve">    &lt;div className=&quot;w-screen h-screen overflow-hidden bg-zinc-950 text-white flex flex-col font-sans&quot;&gt;</w:t><w:br w:type="textWrapping"/><w:t xml:space="preserve">      </w:t><w:br w:type="textWrapping"/><w:t xml:space="preserve">      {/* TOP / MIDDLE SECTION */}</w:t><w:br w:type="textWrapping"/><w:t xml:space="preserve">      &lt;div className=&quot;flex-grow flex relative&quot;&gt;</w:t><w:br w:type="textWrapping"/><w:t xml:space="preserve">        </w:t><w:br w:type="textWrapping"/><w:t xml:space="preserve">        {/* LEFT: Director's Log (Fixed width, translucent) */}</w:t><w:br w:type="textWrapping"/><w:t xml:space="preserve">        &lt;div className=&quot;w-96 bg-zinc-900/90 border-r border-zinc-800 flex flex-col z-10&quot;&gt;</w:t><w:br w:type="textWrapping"/><w:t xml:space="preserve">          &lt;DirectorLog /&gt;</w:t><w:br w:type="textWrapping"/><w:t xml:space="preserve">        &lt;/div&gt;</w:t><w:br w:type="textWrapping"/><w:br w:type="textWrapping"/><w:t xml:space="preserve">        {/* CENTER: The Map (Fills all remaining space) */}</w:t><w:br w:type="textWrapping"/><w:t xml:space="preserve">        &lt;div className=&quot;flex-grow relative bg-black&quot;&gt;</w:t><w:br w:type="textWrapping"/><w:t xml:space="preserve">          &lt;PixiBattlemap /&gt;</w:t><w:br w:type="textWrapping"/><w:t xml:space="preserve">          </w:t><w:br w:type="textWrapping"/><w:t xml:space="preserve">          {/* FLOATING TOP-RIGHT: Quest Tracker */}</w:t><w:br w:type="textWrapping"/><w:t xml:space="preserve">          &lt;div className=&quot;absolute top-4 right-4 z-20 pointer-events-none&quot;&gt;</w:t><w:br w:type="textWrapping"/><w:t xml:space="preserve">            &lt;QuestTracker /&gt;</w:t><w:br w:type="textWrapping"/><w:t xml:space="preserve">          &lt;/div&gt;</w:t><w:br w:type="textWrapping"/><w:t xml:space="preserve">        &lt;/div&gt;</w:t><w:br w:type="textWrapping"/><w:br w:type="textWrapping"/><w:t xml:space="preserve">        {/* RIGHT DRAWER: The Bio-Matrix (Slides in and out) */}</w:t><w:br w:type="textWrapping"/><w:t xml:space="preserve">        {isBioMatrixOpen &amp;&amp; (</w:t><w:br w:type="textWrapping"/><w:t xml:space="preserve">          &lt;div className=&quot;w-1/3 max-w-md bg-zinc-900 border-l border-zinc-800 shadow-2xl z-30 p-4 overflow-y-auto&quot;&gt;</w:t><w:br w:type="textWrapping"/><w:t xml:space="preserve">            &lt;BioMatrix /&gt;</w:t><w:br w:type="textWrapping"/><w:t xml:space="preserve">          &lt;/div&gt;</w:t><w:br w:type="textWrapping"/><w:t xml:space="preserve">        )}</w:t><w:br w:type="textWrapping"/><w:br w:type="textWrapping"/><w:t xml:space="preserve">        {/* Toggle Drawer Button */}</w:t><w:br w:type="textWrapping"/><w:t xml:space="preserve">        &lt;button </w:t><w:br w:type="textWrapping"/><w:t xml:space="preserve">          className=&quot;absolute top-4 right-4 z-40 bg-zinc-800 p-2 rounded hover:bg-zinc-700&quot;</w:t><w:br w:type="textWrapping"/><w:t xml:space="preserve">          onClick={() =&gt; setBioMatrixOpen(!isBioMatrixOpen)}</w:t><w:br w:type="textWrapping"/><w:t xml:space="preserve">        &gt;</w:t><w:br w:type="textWrapping"/><w:t xml:space="preserve">          {isBioMatrixOpen ? 'Close Matrix' : 'Open Matrix'}</w:t><w:br w:type="textWrapping"/><w:t xml:space="preserve">        &lt;/button&gt;</w:t><w:br w:type="textWrapping"/><w:t xml:space="preserve">      &lt;/div&gt;</w:t><w:br w:type="textWrapping"/><w:br w:type="textWrapping"/><w:t xml:space="preserve">      {/* BOTTOM SECTION: The Action Deck (Fixed Height) */}</w:t><w:br w:type="textWrapping"/><w:t xml:space="preserve">      &lt;div className=&quot;h-48 bg-zinc-950 border-t border-zinc-800 z-20 flex justify-center items-center shadow-[0_-10px_40px_rgba(0,0,0,0.5)]&quot;&gt;</w:t><w:br w:type="textWrapping"/><w:t xml:space="preserve">        &lt;ActionDeck /&gt;</w:t><w:br w:type="textWrapping"/><w:t xml:space="preserve">      &lt;/div&gt;</w:t><w:br w:type="textWrapping"/><w:br w:type="textWrapping"/><w:t xml:space="preserve">    &lt;/div&gt;</w:t><w:br w:type="textWrapping"/><w:t xml:space="preserve">  );</w:t><w:br w:type="textWrapping"/><w:t xml:space="preserve">}</w:t><w:br w:type="textWrapping"/></w:r></w:p><w:p w:rsidR="00000000" w:rsidDel="00000000" w:rsidP="00000000" w:rsidRDefault="00000000" w:rsidRPr="00000000" w14:paraId="00000013"><w:pPr><w:pStyle w:val="Heading2"/><w:pBdr><w:top w:space="0" w:sz="0" w:val="nil"/><w:left w:space="0" w:sz="0" w:val="nil"/><w:bottom w:space="0" w:sz="0" w:val="nil"/><w:right w:space="0" w:sz="0" w:val="nil"/><w:between w:space="0" w:sz="0" w:val="nil"/></w:pBdr><w:shd w:fill="auto" w:val="clear"/><w:spacing w:after="120" w:before="120" w:line="275.9999942779541" w:lineRule="auto"/><w:rPr><w:rFonts w:ascii="Google Sans" w:cs="Google Sans" w:eastAsia="Google Sans" w:hAnsi="Google Sans"/><w:color w:val="1f1f1f"/></w:rPr></w:pPr><w:r w:rsidDel="00000000" w:rsidR="00000000" w:rsidRPr="00000000"><w:pict><v:rect style="width:0.0pt;height:1.5pt" o:hr="t" o:hrstd="t" o:hralign="center" fillcolor="#A0A0A0" stroked="f"/></w:pict></w:r><w:r w:rsidDel="00000000" w:rsidR="00000000" w:rsidRPr="00000000"><w:rPr><w:rFonts w:ascii="Google Sans" w:cs="Google Sans" w:eastAsia="Google Sans" w:hAnsi="Google Sans"/><w:color w:val="1f1f1f"/><w:rtl w:val="0"/></w:rPr><w:t xml:space="preserve">3. The Action Deck (components/bottom_console/ActionDeck.tsx)</w:t></w:r></w:p><w:p w:rsidR="00000000" w:rsidDel="00000000" w:rsidP="00000000" w:rsidRDefault="00000000" w:rsidRPr="00000000" w14:paraId="00000014"><w:pPr><w:pBdr><w:top w:space="0" w:sz="0" w:val="nil"/><w:left w:space="0" w:sz="0" w:val="nil"/><w:bottom w:space="0" w:sz="0" w:val="nil"/><w:right w:space="0" w:sz="0" w:val="nil"/><w:between w:space="0" w:sz="0" w:val="nil"/></w:pBdr><w:shd w:fill="auto" w:val="clear"/><w:spacing w:after="240" w:line="275.9999942779541" w:lineRule="auto"/><w:rPr><w:rFonts w:ascii="Google Sans" w:cs="Google Sans" w:eastAsia="Google Sans" w:hAnsi="Google Sans"/><w:color w:val="1f1f1f"/></w:rPr></w:pPr><w:r w:rsidDel="00000000" w:rsidR="00000000" w:rsidRPr="00000000"><w:rPr><w:rFonts w:ascii="Google Sans" w:cs="Google Sans" w:eastAsia="Google Sans" w:hAnsi="Google Sans"/><w:color w:val="1f1f1f"/><w:rtl w:val="0"/></w:rPr><w:t xml:space="preserve">This is the most important tactical component. It visualizes your strict </w:t></w:r><w:r w:rsidDel="00000000" w:rsidR="00000000" w:rsidRPr="00000000"><w:rPr><w:rFonts w:ascii="Google Sans" w:cs="Google Sans" w:eastAsia="Google Sans" w:hAnsi="Google Sans"/><w:b w:val="1"/><w:bCs w:val="1"/><w:color w:val="1f1f1f"/><w:rtl w:val="0"/></w:rPr><w:t xml:space="preserve">Stamina (Body)</w:t></w:r><w:r w:rsidDel="00000000" w:rsidR="00000000" w:rsidRPr="00000000"><w:rPr><w:rFonts w:ascii="Google Sans" w:cs="Google Sans" w:eastAsia="Google Sans" w:hAnsi="Google Sans"/><w:color w:val="1f1f1f"/><w:rtl w:val="0"/></w:rPr><w:t xml:space="preserve"> and </w:t></w:r><w:r w:rsidDel="00000000" w:rsidR="00000000" w:rsidRPr="00000000"><w:rPr><w:rFonts w:ascii="Google Sans" w:cs="Google Sans" w:eastAsia="Google Sans" w:hAnsi="Google Sans"/><w:b w:val="1"/><w:bCs w:val="1"/><w:color w:val="1f1f1f"/><w:rtl w:val="0"/></w:rPr><w:t xml:space="preserve">Focus (Mind)</w:t></w:r><w:r w:rsidDel="00000000" w:rsidR="00000000" w:rsidRPr="00000000"><w:rPr><w:rFonts w:ascii="Google Sans" w:cs="Google Sans" w:eastAsia="Google Sans" w:hAnsi="Google Sans"/><w:color w:val="1f1f1f"/><w:rtl w:val="0"/></w:rPr><w:t xml:space="preserve"> rules, along with the &quot;Burn Slider&quot; for Tactical Grit.</w:t></w:r></w:p><w:p w:rsidR="00000000" w:rsidDel="00000000" w:rsidP="00000000" w:rsidRDefault="00000000" w:rsidRPr="00000000" w14:paraId="00000015"><w:pPr><w:pBdr><w:top w:space="0" w:sz="0" w:val="nil"/><w:left w:space="0" w:sz="0" w:val="nil"/><w:bottom w:space="0" w:sz="0" w:val="nil"/><w:right w:space="0" w:sz="0" w:val="nil"/><w:between w:space="0" w:sz="0" w:val="nil"/></w:pBdr><w:shd w:fill="auto" w:val="clear"/><w:spacing w:after="240" w:line="275.9999942779541" w:lineRule="auto"/><w:ind w:left="240" w:right="120" w:firstLine="0"/><w:rPr><w:rFonts w:ascii="Google Sans" w:cs="Google Sans" w:eastAsia="Google Sans" w:hAnsi="Google Sans"/><w:color w:val="1f1f1f"/></w:rPr></w:pPr><w:r w:rsidDel="00000000" w:rsidR="00000000" w:rsidRPr="00000000"><w:rPr><w:rtl w:val="0"/></w:rPr></w:r></w:p><w:p w:rsidR="00000000" w:rsidDel="00000000" w:rsidP="00000000" w:rsidRDefault="00000000" w:rsidRPr="00000000" w14:paraId="00000016"><w:pPr><w:pBdr><w:top w:space="0" w:sz="0" w:val="nil"/><w:left w:space="0" w:sz="0" w:val="nil"/><w:bottom w:space="0" w:sz="0" w:val="nil"/><w:right w:space="0" w:sz="0" w:val="nil"/><w:between w:space="0" w:sz="0" w:val="nil"/></w:pBdr><w:shd w:fill="auto" w:val="clear"/><w:spacing w:after="150" w:before="120" w:line="275.9999942779541" w:lineRule="auto"/><w:ind w:left="240" w:right="120" w:firstLine="0"/><w:rPr><w:rFonts w:ascii="Google Sans" w:cs="Google Sans" w:eastAsia="Google Sans" w:hAnsi="Google Sans"/><w:color w:val="444746"/><w:shd w:fill="f0f4f9" w:val="clear"/></w:rPr></w:pPr><w:r w:rsidDel="00000000" w:rsidR="00000000" w:rsidRPr="00000000"><w:rPr><w:rFonts w:ascii="Google Sans" w:cs="Google Sans" w:eastAsia="Google Sans" w:hAnsi="Google Sans"/><w:color w:val="444746"/><w:shd w:fill="f0f4f9" w:val="clear"/><w:rtl w:val="0"/></w:rPr><w:t xml:space="preserve">TypeScript</w:t></w:r></w:p><w:p w:rsidR="00000000" w:rsidDel="00000000" w:rsidP="00000000" w:rsidRDefault="00000000" w:rsidRPr="00000000" w14:paraId="00000017"><w:pPr><w:pBdr><w:top w:space="0" w:sz="0" w:val="nil"/><w:left w:space="0" w:sz="0" w:val="nil"/><w:bottom w:space="0" w:sz="0" w:val="nil"/><w:right w:space="0" w:sz="0" w:val="nil"/><w:between w:space="0" w:sz="0" w:val="nil"/></w:pBdr><w:shd w:fill="auto" w:val="clear"/><w:spacing w:line="275.9999942779541" w:lineRule="auto"/><w:rPr><w:rFonts w:ascii="Google Sans" w:cs="Google Sans" w:eastAsia="Google Sans" w:hAnsi="Google Sans"/><w:color w:val="444746"/><w:shd w:fill="f0f4f9" w:val="clear"/></w:rPr></w:pPr><w:r w:rsidDel="00000000" w:rsidR="00000000" w:rsidRPr="00000000"><w:rPr><w:rtl w:val="0"/></w:rPr></w:r></w:p><w:p w:rsidR="00000000" w:rsidDel="00000000" w:rsidP="00000000" w:rsidRDefault="00000000" w:rsidRPr="00000000" w14:paraId="00000018"><w:pPr><w:pBdr><w:top w:space="0" w:sz="0" w:val="nil"/><w:left w:space="0" w:sz="0" w:val="nil"/><w:bottom w:space="0" w:sz="0" w:val="nil"/><w:right w:space="0" w:sz="0" w:val="nil"/><w:between w:space="0" w:sz="0" w:val="nil"/></w:pBdr><w:shd w:fill="auto" w:val="clear"/><w:spacing w:line="275.9999942779541" w:lineRule="auto"/><w:rPr><w:rFonts w:ascii="Google Sans" w:cs="Google Sans" w:eastAsia="Google Sans" w:hAnsi="Google Sans"/><w:color w:val="444746"/><w:shd w:fill="f0f4f9" w:val="clear"/></w:rPr></w:pPr><w:r w:rsidDel="00000000" w:rsidR="00000000" w:rsidRPr="00000000"><w:rPr><w:rtl w:val="0"/></w:rPr></w:r></w:p><w:p w:rsidR="00000000" w:rsidDel="00000000" w:rsidP="00000000" w:rsidRDefault="00000000" w:rsidRPr="00000000" w14:paraId="00000019"><w:pPr><w:pBdr><w:top w:space="0" w:sz="0" w:val="nil"/><w:left w:space="0" w:sz="0" w:val="nil"/><w:bottom w:space="0" w:sz="0" w:val="nil"/><w:right w:space="0" w:sz="0" w:val="nil"/><w:between w:space="0" w:sz="0" w:val="nil"/></w:pBdr><w:shd w:fill="auto" w:val="clear"/><w:spacing w:line="275.9999942779541" w:lineRule="auto"/><w:rPr><w:rFonts w:ascii="Google Sans" w:cs="Google Sans" w:eastAsia="Google Sans" w:hAnsi="Google Sans"/><w:color w:val="1f1f1f"/><w:shd w:fill="f0f4f9" w:val="clear"/></w:rPr></w:pPr><w:r w:rsidDel="00000000" w:rsidR="00000000" w:rsidRPr="00000000"><w:rPr><w:rFonts w:ascii="Google Sans" w:cs="Google Sans" w:eastAsia="Google Sans" w:hAnsi="Google Sans"/><w:color w:val="1f1f1f"/><w:shd w:fill="f0f4f9" w:val="clear"/><w:rtl w:val="0"/></w:rPr><w:t xml:space="preserve">import React, { useState } from 'react';</w:t><w:br w:type="textWrapping"/><w:br w:type="textWrapping"/><w:t xml:space="preserve">export function ActionDeck() {</w:t><w:br w:type="textWrapping"/><w:t xml:space="preserve">  // In a real app, these come from your JSON State Store</w:t><w:br w:type="textWrapping"/><w:t xml:space="preserve">  const maxStamina = 12;</w:t><w:br w:type="textWrapping"/><w:t xml:space="preserve">  const currentStamina = 8;</w:t><w:br w:type="textWrapping"/><w:t xml:space="preserve">  const [burnAmount, setBurnAmount] = useState(0);</w:t><w:br w:type="textWrapping"/><w:br w:type="textWrapping"/><w:t xml:space="preserve">  return (</w:t><w:br w:type="textWrapping"/><w:t xml:space="preserve">    &lt;div className=&quot;flex w-full max-w-6xl h-full items-end pb-4 px-6 gap-8&quot;&gt;</w:t><w:br w:type="textWrapping"/><w:t xml:space="preserve">      </w:t><w:br w:type="textWrapping"/><w:t xml:space="preserve">      {/* LEFT: Stamina Orb/Bar */}</w:t><w:br w:type="textWrapping"/><w:t xml:space="preserve">      &lt;div className=&quot;flex flex-col items-center w-32&quot;&gt;</w:t><w:br w:type="textWrapping"/><w:t xml:space="preserve">        &lt;span className=&quot;text-red-500 font-bold tracking-widest text-sm mb-2&quot;&gt;STAMINA&lt;/span&gt;</w:t><w:br w:type="textWrapping"/><w:t xml:space="preserve">        &lt;div className=&quot;w-24 h-24 rounded-full border-4 border-zinc-800 bg-zinc-900 relative overflow-hidden shadow-[0_0_20px_rgba(239,68,68,0.2)]&quot;&gt;</w:t><w:br w:type="textWrapping"/><w:t xml:space="preserve">          {/* The Red Liquid Fill */}</w:t><w:br w:type="textWrapping"/><w:t xml:space="preserve">          &lt;div </w:t><w:br w:type="textWrapping"/><w:t xml:space="preserve">            className=&quot;absolute bottom-0 w-full bg-red-600 transition-all duration-500&quot;</w:t><w:br w:type="textWrapping"/><w:t xml:space="preserve">            style={{ height: `${(currentStamina / maxStamina) * 100}%` }}</w:t><w:br w:type="textWrapping"/><w:t xml:space="preserve">          /&gt;</w:t><w:br w:type="textWrapping"/><w:t xml:space="preserve">          {/* Center Text */}</w:t><w:br w:type="textWrapping"/><w:t xml:space="preserve">          &lt;div className=&quot;absolute inset-0 flex items-center justify-center font-bold text-2xl text-white drop-shadow-md&quot;&gt;</w:t><w:br w:type="textWrapping"/><w:t xml:space="preserve">            {currentStamina}</w:t><w:br w:type="textWrapping"/><w:t xml:space="preserve">          &lt;/div&gt;</w:t><w:br w:type="textWrapping"/><w:t xml:space="preserve">        &lt;/div&gt;</w:t><w:br w:type="textWrapping"/><w:t xml:space="preserve">      &lt;/div&gt;</w:t><w:br w:type="textWrapping"/><w:br w:type="textWrapping"/><w:t xml:space="preserve">      {/* CENTER: The Skills &amp; Burn Slider */}</w:t><w:br w:type="textWrapping"/><w:t xml:space="preserve">      &lt;div className=&quot;flex-grow flex flex-col justify-end gap-4&quot;&gt;</w:t><w:br w:type="textWrapping"/><w:t xml:space="preserve">        {/* Tactical Grit Burn Slider */}</w:t><w:br w:type="textWrapping"/><w:t xml:space="preserve">        &lt;div className=&quot;flex items-center gap-4 bg-zinc-900/50 p-2 rounded-lg border border-zinc-800&quot;&gt;</w:t><w:br w:type="textWrapping"/><w:t xml:space="preserve">          &lt;span className=&quot;text-zinc-400 text-xs uppercase font-bold&quot;&gt;Burn Stamina (Grit):&lt;/span&gt;</w:t><w:br w:type="textWrapping"/><w:t xml:space="preserve">          &lt;input </w:t><w:br w:type="textWrapping"/><w:t xml:space="preserve">            type=&quot;range&quot; min=&quot;0&quot; max={currentStamina} </w:t><w:br w:type="textWrapping"/><w:t xml:space="preserve">            value={burnAmount} onChange={(e) =&gt; setBurnAmount(Number(e.target.value))}</w:t><w:br w:type="textWrapping"/><w:t xml:space="preserve">            className=&quot;flex-grow accent-red-500&quot;</w:t><w:br w:type="textWrapping"/><w:t xml:space="preserve">          /&gt;</w:t><w:br w:type="textWrapping"/><w:t xml:space="preserve">          &lt;span className=&quot;text-red-500 font-bold&quot;&gt;+{burnAmount}&lt;/span&gt;</w:t><w:br w:type="textWrapping"/><w:t xml:space="preserve">        &lt;/div&gt;</w:t><w:br w:type="textWrapping"/><w:br w:type="textWrapping"/><w:t xml:space="preserve">        {/* Skill Buttons */}</w:t><w:br w:type="textWrapping"/><w:t xml:space="preserve">        &lt;div className=&quot;flex justify-center gap-2&quot;&gt;</w:t><w:br w:type="textWrapping"/><w:t xml:space="preserve">          {['Assault', 'Coercion', 'Mobility', 'Precise Shot'].map(skill =&gt; (</w:t><w:br w:type="textWrapping"/><w:t xml:space="preserve">            &lt;button key={skill} className=&quot;px-6 py-4 bg-zinc-800 hover:bg-red-900 border-b-4 border-zinc-950 rounded text-sm font-bold uppercase tracking-wider transition-colors&quot;&gt;</w:t><w:br w:type="textWrapping"/><w:t xml:space="preserve">              {skill}</w:t><w:br w:type="textWrapping"/><w:t xml:space="preserve">            &lt;/button&gt;</w:t><w:br w:type="textWrapping"/><w:t xml:space="preserve">          ))}</w:t><w:br w:type="textWrapping"/><w:t xml:space="preserve">        &lt;/div&gt;</w:t><w:br w:type="textWrapping"/><w:t xml:space="preserve">      &lt;/div&gt;</w:t><w:br w:type="textWrapping"/><w:br w:type="textWrapping"/><w:t xml:space="preserve">      {/* RIGHT: Quick Inventory (Hedge Charms) */}</w:t><w:br w:type="textWrapping"/><w:t xml:space="preserve">      &lt;div className=&quot;flex gap-2 items-end&quot;&gt;</w:t><w:br w:type="textWrapping"/><w:t xml:space="preserve">        {[1, 2, 3].map(slot =&gt; (</w:t><w:br w:type="textWrapping"/><w:t xml:space="preserve">          &lt;div key={slot} className=&quot;w-16 h-16 bg-zinc-900 border-2 border-zinc-700 rounded-md flex items-center justify-center hover:border-zinc-500 cursor-pointer&quot;&gt;</w:t><w:br w:type="textWrapping"/><w:t xml:space="preserve">            &lt;span className=&quot;text-zinc-600 text-xs&quot;&gt;Slot {slot}&lt;/span&gt;</w:t><w:br w:type="textWrapping"/><w:t xml:space="preserve">          &lt;/div&gt;</w:t><w:br w:type="textWrapping"/><w:t xml:space="preserve">        ))}</w:t><w:br w:type="textWrapping"/><w:t xml:space="preserve">      &lt;/div&gt;</w:t><w:br w:type="textWrapping"/><w:br w:type="textWrapping"/><w:t xml:space="preserve">    &lt;/div&gt;</w:t><w:br w:type="textWrapping"/><w:t xml:space="preserve">  );</w:t><w:br w:type="textWrapping"/><w:t xml:space="preserve">}</w:t><w:br w:type="textWrapping"/></w:r></w:p><w:p w:rsidR="00000000" w:rsidDel="00000000" w:rsidP="00000000" w:rsidRDefault="00000000" w:rsidRPr="00000000" w14:paraId="0000001A"><w:pPr><w:pStyle w:val="Heading2"/><w:pBdr><w:top w:space="0" w:sz="0" w:val="nil"/><w:left w:space="0" w:sz="0" w:val="nil"/><w:bottom w:space="0" w:sz="0" w:val="nil"/><w:right w:space="0" w:sz="0" w:val="nil"/><w:between w:space="0" w:sz="0" w:val="nil"/></w:pBdr><w:shd w:fill="auto" w:val="clear"/><w:spacing w:after="120" w:before="120" w:line="275.9999942779541" w:lineRule="auto"/><w:rPr><w:rFonts w:ascii="Google Sans" w:cs="Google Sans" w:eastAsia="Google Sans" w:hAnsi="Google Sans"/><w:color w:val="1f1f1f"/></w:rPr></w:pPr><w:r w:rsidDel="00000000" w:rsidR="00000000" w:rsidRPr="00000000"><w:pict><v:rect style="width:0.0pt;height:1.5pt" o:hr="t" o:hrstd="t" o:hralign="center" fillcolor="#A0A0A0" stroked="f"/></w:pict></w:r><w:r w:rsidDel="00000000" w:rsidR="00000000" w:rsidRPr="00000000"><w:rPr><w:rFonts w:ascii="Google Sans" w:cs="Google Sans" w:eastAsia="Google Sans" w:hAnsi="Google Sans"/><w:color w:val="1f1f1f"/><w:rtl w:val="0"/></w:rPr><w:t xml:space="preserve">4. The Data Contract (How it stays standalone)</w:t></w:r></w:p><w:p w:rsidR="00000000" w:rsidDel="00000000" w:rsidP="00000000" w:rsidRDefault="00000000" w:rsidRPr="00000000" w14:paraId="0000001B"><w:pPr><w:pBdr><w:top w:space="0" w:sz="0" w:val="nil"/><w:left w:space="0" w:sz="0" w:val="nil"/><w:bottom w:space="0" w:sz="0" w:val="nil"/><w:right w:space="0" w:sz="0" w:val="nil"/><w:between w:space="0" w:sz="0" w:val="nil"/></w:pBdr><w:shd w:fill="auto" w:val="clear"/><w:spacing w:after="240" w:line="275.9999942779541" w:lineRule="auto"/><w:rPr><w:rFonts w:ascii="Google Sans" w:cs="Google Sans" w:eastAsia="Google Sans" w:hAnsi="Google Sans"/><w:color w:val="1f1f1f"/></w:rPr></w:pPr><w:r w:rsidDel="00000000" w:rsidR="00000000" w:rsidRPr="00000000"><w:rPr><w:rFonts w:ascii="Google Sans" w:cs="Google Sans" w:eastAsia="Google Sans" w:hAnsi="Google Sans"/><w:color w:val="1f1f1f"/><w:rtl w:val="0"/></w:rPr><w:t xml:space="preserve">To keep this UI completely decoupled from the AI and the backend, you define a single &quot;State Interface&quot; (e.g., in useGameStore.ts).</w:t></w:r></w:p><w:p w:rsidR="00000000" w:rsidDel="00000000" w:rsidP="00000000" w:rsidRDefault="00000000" w:rsidRPr="00000000" w14:paraId="0000001C"><w:pPr><w:pBdr><w:top w:space="0" w:sz="0" w:val="nil"/><w:left w:space="0" w:sz="0" w:val="nil"/><w:bottom w:space="0" w:sz="0" w:val="nil"/><w:right w:space="0" w:sz="0" w:val="nil"/><w:between w:space="0" w:sz="0" w:val="nil"/></w:pBdr><w:shd w:fill="auto" w:val="clear"/><w:spacing w:after="240" w:line="275.9999942779541" w:lineRule="auto"/><w:rPr><w:rFonts w:ascii="Google Sans" w:cs="Google Sans" w:eastAsia="Google Sans" w:hAnsi="Google Sans"/><w:color w:val="1f1f1f"/></w:rPr></w:pPr><w:r w:rsidDel="00000000" w:rsidR="00000000" w:rsidRPr="00000000"><w:rPr><w:rFonts w:ascii="Google Sans" w:cs="Google Sans" w:eastAsia="Google Sans" w:hAnsi="Google Sans"/><w:color w:val="1f1f1f"/><w:rtl w:val="0"/></w:rPr><w:t xml:space="preserve">The UI </w:t></w:r><w:r w:rsidDel="00000000" w:rsidR="00000000" w:rsidRPr="00000000"><w:rPr><w:rFonts w:ascii="Google Sans" w:cs="Google Sans" w:eastAsia="Google Sans" w:hAnsi="Google Sans"/><w:b w:val="1"/><w:bCs w:val="1"/><w:color w:val="1f1f1f"/><w:rtl w:val="0"/></w:rPr><w:t xml:space="preserve">only</w:t></w:r><w:r w:rsidDel="00000000" w:rsidR="00000000" w:rsidRPr="00000000"><w:rPr><w:rFonts w:ascii="Google Sans" w:cs="Google Sans" w:eastAsia="Google Sans" w:hAnsi="Google Sans"/><w:color w:val="1f1f1f"/><w:rtl w:val="0"/></w:rPr><w:t xml:space="preserve"> reads from this object.</w:t></w:r></w:p><w:p w:rsidR="00000000" w:rsidDel="00000000" w:rsidP="00000000" w:rsidRDefault="00000000" w:rsidRPr="00000000" w14:paraId="0000001D"><w:pPr><w:pBdr><w:top w:space="0" w:sz="0" w:val="nil"/><w:left w:space="0" w:sz="0" w:val="nil"/><w:bottom w:space="0" w:sz="0" w:val="nil"/><w:right w:space="0" w:sz="0" w:val="nil"/><w:between w:space="0" w:sz="0" w:val="nil"/></w:pBdr><w:shd w:fill="auto" w:val="clear"/><w:spacing w:after="240" w:line="275.9999942779541" w:lineRule="auto"/><w:ind w:left="240" w:right="120" w:firstLine="0"/><w:rPr><w:rFonts w:ascii="Google Sans" w:cs="Google Sans" w:eastAsia="Google Sans" w:hAnsi="Google Sans"/><w:color w:val="1f1f1f"/></w:rPr></w:pPr><w:r w:rsidDel="00000000" w:rsidR="00000000" w:rsidRPr="00000000"><w:rPr><w:rtl w:val="0"/></w:rPr></w:r></w:p><w:p w:rsidR="00000000" w:rsidDel="00000000" w:rsidP="00000000" w:rsidRDefault="00000000" w:rsidRPr="00000000" w14:paraId="0000001E"><w:pPr><w:pBdr><w:top w:space="0" w:sz="0" w:val="nil"/><w:left w:space="0" w:sz="0" w:val="nil"/><w:bottom w:space="0" w:sz="0" w:val="nil"/><w:right w:space="0" w:sz="0" w:val="nil"/><w:between w:space="0" w:sz="0" w:val="nil"/></w:pBdr><w:shd w:fill="auto" w:val="clear"/><w:spacing w:after="150" w:before="120" w:line="275.9999942779541" w:lineRule="auto"/><w:ind w:left="240" w:right="120" w:firstLine="0"/><w:rPr><w:rFonts w:ascii="Google Sans" w:cs="Google Sans" w:eastAsia="Google Sans" w:hAnsi="Google Sans"/><w:color w:val="444746"/><w:shd w:fill="f0f4f9" w:val="clear"/></w:rPr></w:pPr><w:r w:rsidDel="00000000" w:rsidR="00000000" w:rsidRPr="00000000"><w:rPr><w:rFonts w:ascii="Google Sans" w:cs="Google Sans" w:eastAsia="Google Sans" w:hAnsi="Google Sans"/><w:color w:val="444746"/><w:shd w:fill="f0f4f9" w:val="clear"/><w:rtl w:val="0"/></w:rPr><w:t xml:space="preserve">TypeScript</w:t></w:r></w:p><w:p w:rsidR="00000000" w:rsidDel="00000000" w:rsidP="00000000" w:rsidRDefault="00000000" w:rsidRPr="00000000" w14:paraId="0000001F"><w:pPr><w:pBdr><w:top w:space="0" w:sz="0" w:val="nil"/><w:left w:space="0" w:sz="0" w:val="nil"/><w:bottom w:space="0" w:sz="0" w:val="nil"/><w:right w:space="0" w:sz="0" w:val="nil"/><w:between w:space="0" w:sz="0" w:val="nil"/></w:pBdr><w:shd w:fill="auto" w:val="clear"/><w:spacing w:line="275.9999942779541" w:lineRule="auto"/><w:rPr><w:rFonts w:ascii="Google Sans" w:cs="Google Sans" w:eastAsia="Google Sans" w:hAnsi="Google Sans"/><w:color w:val="444746"/><w:shd w:fill="f0f4f9" w:val="clear"/></w:rPr></w:pPr><w:r w:rsidDel="00000000" w:rsidR="00000000" w:rsidRPr="00000000"><w:rPr><w:rtl w:val="0"/></w:rPr></w:r></w:p><w:p w:rsidR="00000000" w:rsidDel="00000000" w:rsidP="00000000" w:rsidRDefault="00000000" w:rsidRPr="00000000" w14:paraId="00000020"><w:pPr><w:pBdr><w:top w:space="0" w:sz="0" w:val="nil"/><w:left w:space="0" w:sz="0" w:val="nil"/><w:bottom w:space="0" w:sz="0" w:val="nil"/><w:right w:space="0" w:sz="0" w:val="nil"/><w:between w:space="0" w:sz="0" w:val="nil"/></w:pBdr><w:shd w:fill="auto" w:val="clear"/><w:spacing w:line="275.9999942779541" w:lineRule="auto"/><w:rPr><w:rFonts w:ascii="Google Sans" w:cs="Google Sans" w:eastAsia="Google Sans" w:hAnsi="Google Sans"/><w:color w:val="444746"/><w:shd w:fill="f0f4f9" w:val="clear"/></w:rPr></w:pPr><w:r w:rsidDel="00000000" w:rsidR="00000000" w:rsidRPr="00000000"><w:rPr><w:rtl w:val="0"/></w:rPr></w:r></w:p><w:p w:rsidR="00000000" w:rsidDel="00000000" w:rsidP="00000000" w:rsidRDefault="00000000" w:rsidRPr="00000000" w14:paraId="00000021"><w:pPr><w:pBdr><w:top w:space="0" w:sz="0" w:val="nil"/><w:left w:space="0" w:sz="0" w:val="nil"/><w:bottom w:space="0" w:sz="0" w:val="nil"/><w:right w:space="0" w:sz="0" w:val="nil"/><w:between w:space="0" w:sz="0" w:val="nil"/></w:pBdr><w:shd w:fill="auto" w:val="clear"/><w:spacing w:line="275.9999942779541" w:lineRule="auto"/><w:rPr><w:rFonts w:ascii="Google Sans" w:cs="Google Sans" w:eastAsia="Google Sans" w:hAnsi="Google Sans"/><w:color w:val="1f1f1f"/><w:shd w:fill="f0f4f9" w:val="clear"/></w:rPr></w:pPr><w:r w:rsidDel="00000000" w:rsidR="00000000" w:rsidRPr="00000000"><w:rPr><w:rFonts w:ascii="Google Sans" w:cs="Google Sans" w:eastAsia="Google Sans" w:hAnsi="Google Sans"/><w:i w:val="0"/><w:iCs w:val="0"/><w:color w:val="8430ce"/><w:sz w:val="20"/><w:szCs w:val="20"/><w:shd w:fill="f0f4f9" w:val="clear"/><w:rtl w:val="0"/></w:rPr><w:t xml:space="preserve">interface</w:t></w:r><w:r w:rsidDel="00000000" w:rsidR="00000000" w:rsidRPr="00000000"><w:rPr><w:rFonts w:ascii="Google Sans" w:cs="Google Sans" w:eastAsia="Google Sans" w:hAnsi="Google Sans"/><w:color w:val="1f1f1f"/><w:shd w:fill="f0f4f9" w:val="clear"/><w:rtl w:val="0"/></w:rPr><w:t xml:space="preserve"> ClientGameState {</w:t><w:br w:type="textWrapping"/><w:t xml:space="preserve">  </w:t></w:r><w:r w:rsidDel="00000000" w:rsidR="00000000" w:rsidRPr="00000000"><w:rPr><w:rFonts w:ascii="Google Sans" w:cs="Google Sans" w:eastAsia="Google Sans" w:hAnsi="Google Sans"/><w:i w:val="0"/><w:iCs w:val="0"/><w:color w:val="b55908"/><w:sz w:val="20"/><w:szCs w:val="20"/><w:shd w:fill="f0f4f9" w:val="clear"/><w:rtl w:val="0"/></w:rPr><w:t xml:space="preserve">ui_locked</w:t></w:r><w:r w:rsidDel="00000000" w:rsidR="00000000" w:rsidRPr="00000000"><w:rPr><w:rFonts w:ascii="Google Sans" w:cs="Google Sans" w:eastAsia="Google Sans" w:hAnsi="Google Sans"/><w:color w:val="1f1f1f"/><w:shd w:fill="f0f4f9" w:val="clear"/><w:rtl w:val="0"/></w:rPr><w:t xml:space="preserve">: </w:t></w:r><w:r w:rsidDel="00000000" w:rsidR="00000000" w:rsidRPr="00000000"><w:rPr><w:rFonts w:ascii="Google Sans" w:cs="Google Sans" w:eastAsia="Google Sans" w:hAnsi="Google Sans"/><w:i w:val="0"/><w:iCs w:val="0"/><w:color w:val="1967d2"/><w:sz w:val="20"/><w:szCs w:val="20"/><w:shd w:fill="f0f4f9" w:val="clear"/><w:rtl w:val="0"/></w:rPr><w:t xml:space="preserve">boolean</w:t></w:r><w:r w:rsidDel="00000000" w:rsidR="00000000" w:rsidRPr="00000000"><w:rPr><w:rFonts w:ascii="Google Sans" w:cs="Google Sans" w:eastAsia="Google Sans" w:hAnsi="Google Sans"/><w:color w:val="1f1f1f"/><w:shd w:fill="f0f4f9" w:val="clear"/><w:rtl w:val="0"/></w:rPr><w:t xml:space="preserve">; </w:t></w:r><w:r w:rsidDel="00000000" w:rsidR="00000000" w:rsidRPr="00000000"><w:rPr><w:rFonts w:ascii="Google Sans" w:cs="Google Sans" w:eastAsia="Google Sans" w:hAnsi="Google Sans"/><w:i w:val="0"/><w:iCs w:val="0"/><w:color w:val="5f6368"/><w:sz w:val="20"/><w:szCs w:val="20"/><w:shd w:fill="f0f4f9" w:val="clear"/><w:rtl w:val="0"/></w:rPr><w:t xml:space="preserve">// If true, disable all buttons (Director is talking)</w:t></w:r><w:r w:rsidDel="00000000" w:rsidR="00000000" w:rsidRPr="00000000"><w:rPr><w:rFonts w:ascii="Google Sans" w:cs="Google Sans" w:eastAsia="Google Sans" w:hAnsi="Google Sans"/><w:color w:val="1f1f1f"/><w:shd w:fill="f0f4f9" w:val="clear"/><w:rtl w:val="0"/></w:rPr><w:br w:type="textWrapping"/><w:t xml:space="preserve">  </w:t><w:br w:type="textWrapping"/><w:t xml:space="preserve">  vitals: {</w:t><w:br w:type="textWrapping"/><w:t xml:space="preserve">    </w:t></w:r><w:r w:rsidDel="00000000" w:rsidR="00000000" w:rsidRPr="00000000"><w:rPr><w:rFonts w:ascii="Google Sans" w:cs="Google Sans" w:eastAsia="Google Sans" w:hAnsi="Google Sans"/><w:i w:val="0"/><w:iCs w:val="0"/><w:color w:val="b55908"/><w:sz w:val="20"/><w:szCs w:val="20"/><w:shd w:fill="f0f4f9" w:val="clear"/><w:rtl w:val="0"/></w:rPr><w:t xml:space="preserve">hp</w:t></w:r><w:r w:rsidDel="00000000" w:rsidR="00000000" w:rsidRPr="00000000"><w:rPr><w:rFonts w:ascii="Google Sans" w:cs="Google Sans" w:eastAsia="Google Sans" w:hAnsi="Google Sans"/><w:color w:val="1f1f1f"/><w:shd w:fill="f0f4f9" w:val="clear"/><w:rtl w:val="0"/></w:rPr><w:t xml:space="preserve">: { </w:t></w:r><w:r w:rsidDel="00000000" w:rsidR="00000000" w:rsidRPr="00000000"><w:rPr><w:rFonts w:ascii="Google Sans" w:cs="Google Sans" w:eastAsia="Google Sans" w:hAnsi="Google Sans"/><w:i w:val="0"/><w:iCs w:val="0"/><w:color w:val="b55908"/><w:sz w:val="20"/><w:szCs w:val="20"/><w:shd w:fill="f0f4f9" w:val="clear"/><w:rtl w:val="0"/></w:rPr><w:t xml:space="preserve">current</w:t></w:r><w:r w:rsidDel="00000000" w:rsidR="00000000" w:rsidRPr="00000000"><w:rPr><w:rFonts w:ascii="Google Sans" w:cs="Google Sans" w:eastAsia="Google Sans" w:hAnsi="Google Sans"/><w:color w:val="1f1f1f"/><w:shd w:fill="f0f4f9" w:val="clear"/><w:rtl w:val="0"/></w:rPr><w:t xml:space="preserve">: </w:t></w:r><w:r w:rsidDel="00000000" w:rsidR="00000000" w:rsidRPr="00000000"><w:rPr><w:rFonts w:ascii="Google Sans" w:cs="Google Sans" w:eastAsia="Google Sans" w:hAnsi="Google Sans"/><w:i w:val="0"/><w:iCs w:val="0"/><w:color w:val="1967d2"/><w:sz w:val="20"/><w:szCs w:val="20"/><w:shd w:fill="f0f4f9" w:val="clear"/><w:rtl w:val="0"/></w:rPr><w:t xml:space="preserve">number</w:t></w:r><w:r w:rsidDel="00000000" w:rsidR="00000000" w:rsidRPr="00000000"><w:rPr><w:rFonts w:ascii="Google Sans" w:cs="Google Sans" w:eastAsia="Google Sans" w:hAnsi="Google Sans"/><w:color w:val="1f1f1f"/><w:shd w:fill="f0f4f9" w:val="clear"/><w:rtl w:val="0"/></w:rPr><w:t xml:space="preserve">, </w:t></w:r><w:r w:rsidDel="00000000" w:rsidR="00000000" w:rsidRPr="00000000"><w:rPr><w:rFonts w:ascii="Google Sans" w:cs="Google Sans" w:eastAsia="Google Sans" w:hAnsi="Google Sans"/><w:i w:val="0"/><w:iCs w:val="0"/><w:color w:val="b55908"/><w:sz w:val="20"/><w:szCs w:val="20"/><w:shd w:fill="f0f4f9" w:val="clear"/><w:rtl w:val="0"/></w:rPr><w:t xml:space="preserve">max</w:t></w:r><w:r w:rsidDel="00000000" w:rsidR="00000000" w:rsidRPr="00000000"><w:rPr><w:rFonts w:ascii="Google Sans" w:cs="Google Sans" w:eastAsia="Google Sans" w:hAnsi="Google Sans"/><w:color w:val="1f1f1f"/><w:shd w:fill="f0f4f9" w:val="clear"/><w:rtl w:val="0"/></w:rPr><w:t xml:space="preserve">: </w:t></w:r><w:r w:rsidDel="00000000" w:rsidR="00000000" w:rsidRPr="00000000"><w:rPr><w:rFonts w:ascii="Google Sans" w:cs="Google Sans" w:eastAsia="Google Sans" w:hAnsi="Google Sans"/><w:i w:val="0"/><w:iCs w:val="0"/><w:color w:val="1967d2"/><w:sz w:val="20"/><w:szCs w:val="20"/><w:shd w:fill="f0f4f9" w:val="clear"/><w:rtl w:val="0"/></w:rPr><w:t xml:space="preserve">number</w:t></w:r><w:r w:rsidDel="00000000" w:rsidR="00000000" w:rsidRPr="00000000"><w:rPr><w:rFonts w:ascii="Google Sans" w:cs="Google Sans" w:eastAsia="Google Sans" w:hAnsi="Google Sans"/><w:color w:val="1f1f1f"/><w:shd w:fill="f0f4f9" w:val="clear"/><w:rtl w:val="0"/></w:rPr><w:t xml:space="preserve"> },</w:t><w:br w:type="textWrapping"/><w:t xml:space="preserve">    </w:t></w:r><w:r w:rsidDel="00000000" w:rsidR="00000000" w:rsidRPr="00000000"><w:rPr><w:rFonts w:ascii="Google Sans" w:cs="Google Sans" w:eastAsia="Google Sans" w:hAnsi="Google Sans"/><w:i w:val="0"/><w:iCs w:val="0"/><w:color w:val="b55908"/><w:sz w:val="20"/><w:szCs w:val="20"/><w:shd w:fill="f0f4f9" w:val="clear"/><w:rtl w:val="0"/></w:rPr><w:t xml:space="preserve">stamina</w:t></w:r><w:r w:rsidDel="00000000" w:rsidR="00000000" w:rsidRPr="00000000"><w:rPr><w:rFonts w:ascii="Google Sans" w:cs="Google Sans" w:eastAsia="Google Sans" w:hAnsi="Google Sans"/><w:color w:val="1f1f1f"/><w:shd w:fill="f0f4f9" w:val="clear"/><w:rtl w:val="0"/></w:rPr><w:t xml:space="preserve">: { </w:t></w:r><w:r w:rsidDel="00000000" w:rsidR="00000000" w:rsidRPr="00000000"><w:rPr><w:rFonts w:ascii="Google Sans" w:cs="Google Sans" w:eastAsia="Google Sans" w:hAnsi="Google Sans"/><w:i w:val="0"/><w:iCs w:val="0"/><w:color w:val="b55908"/><w:sz w:val="20"/><w:szCs w:val="20"/><w:shd w:fill="f0f4f9" w:val="clear"/><w:rtl w:val="0"/></w:rPr><w:t xml:space="preserve">current</w:t></w:r><w:r w:rsidDel="00000000" w:rsidR="00000000" w:rsidRPr="00000000"><w:rPr><w:rFonts w:ascii="Google Sans" w:cs="Google Sans" w:eastAsia="Google Sans" w:hAnsi="Google Sans"/><w:color w:val="1f1f1f"/><w:shd w:fill="f0f4f9" w:val="clear"/><w:rtl w:val="0"/></w:rPr><w:t xml:space="preserve">: </w:t></w:r><w:r w:rsidDel="00000000" w:rsidR="00000000" w:rsidRPr="00000000"><w:rPr><w:rFonts w:ascii="Google Sans" w:cs="Google Sans" w:eastAsia="Google Sans" w:hAnsi="Google Sans"/><w:i w:val="0"/><w:iCs w:val="0"/><w:color w:val="1967d2"/><w:sz w:val="20"/><w:szCs w:val="20"/><w:shd w:fill="f0f4f9" w:val="clear"/><w:rtl w:val="0"/></w:rPr><w:t xml:space="preserve">number</w:t></w:r><w:r w:rsidDel="00000000" w:rsidR="00000000" w:rsidRPr="00000000"><w:rPr><w:rFonts w:ascii="Google Sans" w:cs="Google Sans" w:eastAsia="Google Sans" w:hAnsi="Google Sans"/><w:color w:val="1f1f1f"/><w:shd w:fill="f0f4f9" w:val="clear"/><w:rtl w:val="0"/></w:rPr><w:t xml:space="preserve">, </w:t></w:r><w:r w:rsidDel="00000000" w:rsidR="00000000" w:rsidRPr="00000000"><w:rPr><w:rFonts w:ascii="Google Sans" w:cs="Google Sans" w:eastAsia="Google Sans" w:hAnsi="Google Sans"/><w:i w:val="0"/><w:iCs w:val="0"/><w:color w:val="b55908"/><w:sz w:val="20"/><w:szCs w:val="20"/><w:shd w:fill="f0f4f9" w:val="clear"/><w:rtl w:val="0"/></w:rPr><w:t xml:space="preserve">max</w:t></w:r><w:r w:rsidDel="00000000" w:rsidR="00000000" w:rsidRPr="00000000"><w:rPr><w:rFonts w:ascii="Google Sans" w:cs="Google Sans" w:eastAsia="Google Sans" w:hAnsi="Google Sans"/><w:color w:val="1f1f1f"/><w:shd w:fill="f0f4f9" w:val="clear"/><w:rtl w:val="0"/></w:rPr><w:t xml:space="preserve">: </w:t></w:r><w:r w:rsidDel="00000000" w:rsidR="00000000" w:rsidRPr="00000000"><w:rPr><w:rFonts w:ascii="Google Sans" w:cs="Google Sans" w:eastAsia="Google Sans" w:hAnsi="Google Sans"/><w:i w:val="0"/><w:iCs w:val="0"/><w:color w:val="1967d2"/><w:sz w:val="20"/><w:szCs w:val="20"/><w:shd w:fill="f0f4f9" w:val="clear"/><w:rtl w:val="0"/></w:rPr><w:t xml:space="preserve">number</w:t></w:r><w:r w:rsidDel="00000000" w:rsidR="00000000" w:rsidRPr="00000000"><w:rPr><w:rFonts w:ascii="Google Sans" w:cs="Google Sans" w:eastAsia="Google Sans" w:hAnsi="Google Sans"/><w:color w:val="1f1f1f"/><w:shd w:fill="f0f4f9" w:val="clear"/><w:rtl w:val="0"/></w:rPr><w:t xml:space="preserve"> },</w:t><w:br w:type="textWrapping"/><w:t xml:space="preserve">    </w:t></w:r><w:r w:rsidDel="00000000" w:rsidR="00000000" w:rsidRPr="00000000"><w:rPr><w:rFonts w:ascii="Google Sans" w:cs="Google Sans" w:eastAsia="Google Sans" w:hAnsi="Google Sans"/><w:i w:val="0"/><w:iCs w:val="0"/><w:color w:val="b55908"/><w:sz w:val="20"/><w:szCs w:val="20"/><w:shd w:fill="f0f4f9" w:val="clear"/><w:rtl w:val="0"/></w:rPr><w:t xml:space="preserve">focus</w:t></w:r><w:r w:rsidDel="00000000" w:rsidR="00000000" w:rsidRPr="00000000"><w:rPr><w:rFonts w:ascii="Google Sans" w:cs="Google Sans" w:eastAsia="Google Sans" w:hAnsi="Google Sans"/><w:color w:val="1f1f1f"/><w:shd w:fill="f0f4f9" w:val="clear"/><w:rtl w:val="0"/></w:rPr><w:t xml:space="preserve">: { </w:t></w:r><w:r w:rsidDel="00000000" w:rsidR="00000000" w:rsidRPr="00000000"><w:rPr><w:rFonts w:ascii="Google Sans" w:cs="Google Sans" w:eastAsia="Google Sans" w:hAnsi="Google Sans"/><w:i w:val="0"/><w:iCs w:val="0"/><w:color w:val="b55908"/><w:sz w:val="20"/><w:szCs w:val="20"/><w:shd w:fill="f0f4f9" w:val="clear"/><w:rtl w:val="0"/></w:rPr><w:t xml:space="preserve">current</w:t></w:r><w:r w:rsidDel="00000000" w:rsidR="00000000" w:rsidRPr="00000000"><w:rPr><w:rFonts w:ascii="Google Sans" w:cs="Google Sans" w:eastAsia="Google Sans" w:hAnsi="Google Sans"/><w:color w:val="1f1f1f"/><w:shd w:fill="f0f4f9" w:val="clear"/><w:rtl w:val="0"/></w:rPr><w:t xml:space="preserve">: </w:t></w:r><w:r w:rsidDel="00000000" w:rsidR="00000000" w:rsidRPr="00000000"><w:rPr><w:rFonts w:ascii="Google Sans" w:cs="Google Sans" w:eastAsia="Google Sans" w:hAnsi="Google Sans"/><w:i w:val="0"/><w:iCs w:val="0"/><w:color w:val="1967d2"/><w:sz w:val="20"/><w:szCs w:val="20"/><w:shd w:fill="f0f4f9" w:val="clear"/><w:rtl w:val="0"/></w:rPr><w:t xml:space="preserve">number</w:t></w:r><w:r w:rsidDel="00000000" w:rsidR="00000000" w:rsidRPr="00000000"><w:rPr><w:rFonts w:ascii="Google Sans" w:cs="Google Sans" w:eastAsia="Google Sans" w:hAnsi="Google Sans"/><w:color w:val="1f1f1f"/><w:shd w:fill="f0f4f9" w:val="clear"/><w:rtl w:val="0"/></w:rPr><w:t xml:space="preserve">, </w:t></w:r><w:r w:rsidDel="00000000" w:rsidR="00000000" w:rsidRPr="00000000"><w:rPr><w:rFonts w:ascii="Google Sans" w:cs="Google Sans" w:eastAsia="Google Sans" w:hAnsi="Google Sans"/><w:i w:val="0"/><w:iCs w:val="0"/><w:color w:val="b55908"/><w:sz w:val="20"/><w:szCs w:val="20"/><w:shd w:fill="f0f4f9" w:val="clear"/><w:rtl w:val="0"/></w:rPr><w:t xml:space="preserve">max</w:t></w:r><w:r w:rsidDel="00000000" w:rsidR="00000000" w:rsidRPr="00000000"><w:rPr><w:rFonts w:ascii="Google Sans" w:cs="Google Sans" w:eastAsia="Google Sans" w:hAnsi="Google Sans"/><w:color w:val="1f1f1f"/><w:shd w:fill="f0f4f9" w:val="clear"/><w:rtl w:val="0"/></w:rPr><w:t xml:space="preserve">: </w:t></w:r><w:r w:rsidDel="00000000" w:rsidR="00000000" w:rsidRPr="00000000"><w:rPr><w:rFonts w:ascii="Google Sans" w:cs="Google Sans" w:eastAsia="Google Sans" w:hAnsi="Google Sans"/><w:i w:val="0"/><w:iCs w:val="0"/><w:color w:val="1967d2"/><w:sz w:val="20"/><w:szCs w:val="20"/><w:shd w:fill="f0f4f9" w:val="clear"/><w:rtl w:val="0"/></w:rPr><w:t xml:space="preserve">number</w:t></w:r><w:r w:rsidDel="00000000" w:rsidR="00000000" w:rsidRPr="00000000"><w:rPr><w:rFonts w:ascii="Google Sans" w:cs="Google Sans" w:eastAsia="Google Sans" w:hAnsi="Google Sans"/><w:color w:val="1f1f1f"/><w:shd w:fill="f0f4f9" w:val="clear"/><w:rtl w:val="0"/></w:rPr><w:t xml:space="preserve"> },</w:t><w:br w:type="textWrapping"/><w:t xml:space="preserve">    </w:t></w:r><w:r w:rsidDel="00000000" w:rsidR="00000000" w:rsidRPr="00000000"><w:rPr><w:rFonts w:ascii="Google Sans" w:cs="Google Sans" w:eastAsia="Google Sans" w:hAnsi="Google Sans"/><w:i w:val="0"/><w:iCs w:val="0"/><w:color w:val="b55908"/><w:sz w:val="20"/><w:szCs w:val="20"/><w:shd w:fill="f0f4f9" w:val="clear"/><w:rtl w:val="0"/></w:rPr><w:t xml:space="preserve">composure</w:t></w:r><w:r w:rsidDel="00000000" w:rsidR="00000000" w:rsidRPr="00000000"><w:rPr><w:rFonts w:ascii="Google Sans" w:cs="Google Sans" w:eastAsia="Google Sans" w:hAnsi="Google Sans"/><w:color w:val="1f1f1f"/><w:shd w:fill="f0f4f9" w:val="clear"/><w:rtl w:val="0"/></w:rPr><w:t xml:space="preserve">: { </w:t></w:r><w:r w:rsidDel="00000000" w:rsidR="00000000" w:rsidRPr="00000000"><w:rPr><w:rFonts w:ascii="Google Sans" w:cs="Google Sans" w:eastAsia="Google Sans" w:hAnsi="Google Sans"/><w:i w:val="0"/><w:iCs w:val="0"/><w:color w:val="b55908"/><w:sz w:val="20"/><w:szCs w:val="20"/><w:shd w:fill="f0f4f9" w:val="clear"/><w:rtl w:val="0"/></w:rPr><w:t xml:space="preserve">current</w:t></w:r><w:r w:rsidDel="00000000" w:rsidR="00000000" w:rsidRPr="00000000"><w:rPr><w:rFonts w:ascii="Google Sans" w:cs="Google Sans" w:eastAsia="Google Sans" w:hAnsi="Google Sans"/><w:color w:val="1f1f1f"/><w:shd w:fill="f0f4f9" w:val="clear"/><w:rtl w:val="0"/></w:rPr><w:t xml:space="preserve">: </w:t></w:r><w:r w:rsidDel="00000000" w:rsidR="00000000" w:rsidRPr="00000000"><w:rPr><w:rFonts w:ascii="Google Sans" w:cs="Google Sans" w:eastAsia="Google Sans" w:hAnsi="Google Sans"/><w:i w:val="0"/><w:iCs w:val="0"/><w:color w:val="1967d2"/><w:sz w:val="20"/><w:szCs w:val="20"/><w:shd w:fill="f0f4f9" w:val="clear"/><w:rtl w:val="0"/></w:rPr><w:t xml:space="preserve">number</w:t></w:r><w:r w:rsidDel="00000000" w:rsidR="00000000" w:rsidRPr="00000000"><w:rPr><w:rFonts w:ascii="Google Sans" w:cs="Google Sans" w:eastAsia="Google Sans" w:hAnsi="Google Sans"/><w:color w:val="1f1f1f"/><w:shd w:fill="f0f4f9" w:val="clear"/><w:rtl w:val="0"/></w:rPr><w:t xml:space="preserve">, </w:t></w:r><w:r w:rsidDel="00000000" w:rsidR="00000000" w:rsidRPr="00000000"><w:rPr><w:rFonts w:ascii="Google Sans" w:cs="Google Sans" w:eastAsia="Google Sans" w:hAnsi="Google Sans"/><w:i w:val="0"/><w:iCs w:val="0"/><w:color w:val="b55908"/><w:sz w:val="20"/><w:szCs w:val="20"/><w:shd w:fill="f0f4f9" w:val="clear"/><w:rtl w:val="0"/></w:rPr><w:t xml:space="preserve">max</w:t></w:r><w:r w:rsidDel="00000000" w:rsidR="00000000" w:rsidRPr="00000000"><w:rPr><w:rFonts w:ascii="Google Sans" w:cs="Google Sans" w:eastAsia="Google Sans" w:hAnsi="Google Sans"/><w:color w:val="1f1f1f"/><w:shd w:fill="f0f4f9" w:val="clear"/><w:rtl w:val="0"/></w:rPr><w:t xml:space="preserve">: </w:t></w:r><w:r w:rsidDel="00000000" w:rsidR="00000000" w:rsidRPr="00000000"><w:rPr><w:rFonts w:ascii="Google Sans" w:cs="Google Sans" w:eastAsia="Google Sans" w:hAnsi="Google Sans"/><w:i w:val="0"/><w:iCs w:val="0"/><w:color w:val="1967d2"/><w:sz w:val="20"/><w:szCs w:val="20"/><w:shd w:fill="f0f4f9" w:val="clear"/><w:rtl w:val="0"/></w:rPr><w:t xml:space="preserve">number</w:t></w:r><w:r w:rsidDel="00000000" w:rsidR="00000000" w:rsidRPr="00000000"><w:rPr><w:rFonts w:ascii="Google Sans" w:cs="Google Sans" w:eastAsia="Google Sans" w:hAnsi="Google Sans"/><w:color w:val="1f1f1f"/><w:shd w:fill="f0f4f9" w:val="clear"/><w:rtl w:val="0"/></w:rPr><w:t xml:space="preserve"> }</w:t><w:br w:type="textWrapping"/><w:t xml:space="preserve">  };</w:t><w:br w:type="textWrapping"/><w:t xml:space="preserve">  </w:t><w:br w:type="textWrapping"/><w:t xml:space="preserve">  injuries: {</w:t><w:br w:type="textWrapping"/><w:t xml:space="preserve">    </w:t></w:r><w:r w:rsidDel="00000000" w:rsidR="00000000" w:rsidRPr="00000000"><w:rPr><w:rFonts w:ascii="Google Sans" w:cs="Google Sans" w:eastAsia="Google Sans" w:hAnsi="Google Sans"/><w:i w:val="0"/><w:iCs w:val="0"/><w:color w:val="b55908"/><w:sz w:val="20"/><w:szCs w:val="20"/><w:shd w:fill="f0f4f9" w:val="clear"/><w:rtl w:val="0"/></w:rPr><w:t xml:space="preserve">body</w:t></w:r><w:r w:rsidDel="00000000" w:rsidR="00000000" w:rsidRPr="00000000"><w:rPr><w:rFonts w:ascii="Google Sans" w:cs="Google Sans" w:eastAsia="Google Sans" w:hAnsi="Google Sans"/><w:color w:val="1f1f1f"/><w:shd w:fill="f0f4f9" w:val="clear"/><w:rtl w:val="0"/></w:rPr><w:t xml:space="preserve">: </w:t></w:r><w:r w:rsidDel="00000000" w:rsidR="00000000" w:rsidRPr="00000000"><w:rPr><w:rFonts w:ascii="Google Sans" w:cs="Google Sans" w:eastAsia="Google Sans" w:hAnsi="Google Sans"/><w:i w:val="0"/><w:iCs w:val="0"/><w:color w:val="1967d2"/><w:sz w:val="20"/><w:szCs w:val="20"/><w:shd w:fill="f0f4f9" w:val="clear"/><w:rtl w:val="0"/></w:rPr><w:t xml:space="preserve">string</w:t></w:r><w:r w:rsidDel="00000000" w:rsidR="00000000" w:rsidRPr="00000000"><w:rPr><w:rFonts w:ascii="Google Sans" w:cs="Google Sans" w:eastAsia="Google Sans" w:hAnsi="Google Sans"/><w:color w:val="1f1f1f"/><w:shd w:fill="f0f4f9" w:val="clear"/><w:rtl w:val="0"/></w:rPr><w:t xml:space="preserve">[]; </w:t></w:r><w:r w:rsidDel="00000000" w:rsidR="00000000" w:rsidRPr="00000000"><w:rPr><w:rFonts w:ascii="Google Sans" w:cs="Google Sans" w:eastAsia="Google Sans" w:hAnsi="Google Sans"/><w:i w:val="0"/><w:iCs w:val="0"/><w:color w:val="5f6368"/><w:sz w:val="20"/><w:szCs w:val="20"/><w:shd w:fill="f0f4f9" w:val="clear"/><w:rtl w:val="0"/></w:rPr><w:t xml:space="preserve">// e.g., [&quot;Shattered Limb&quot;]</w:t></w:r><w:r w:rsidDel="00000000" w:rsidR="00000000" w:rsidRPr="00000000"><w:rPr><w:rFonts w:ascii="Google Sans" w:cs="Google Sans" w:eastAsia="Google Sans" w:hAnsi="Google Sans"/><w:color w:val="1f1f1f"/><w:shd w:fill="f0f4f9" w:val="clear"/><w:rtl w:val="0"/></w:rPr><w:br w:type="textWrapping"/><w:t xml:space="preserve">    mind: </w:t></w:r><w:r w:rsidDel="00000000" w:rsidR="00000000" w:rsidRPr="00000000"><w:rPr><w:rFonts w:ascii="Google Sans" w:cs="Google Sans" w:eastAsia="Google Sans" w:hAnsi="Google Sans"/><w:i w:val="0"/><w:iCs w:val="0"/><w:color w:val="1967d2"/><w:sz w:val="20"/><w:szCs w:val="20"/><w:shd w:fill="f0f4f9" w:val="clear"/><w:rtl w:val="0"/></w:rPr><w:t xml:space="preserve">string</w:t></w:r><w:r w:rsidDel="00000000" w:rsidR="00000000" w:rsidRPr="00000000"><w:rPr><w:rFonts w:ascii="Google Sans" w:cs="Google Sans" w:eastAsia="Google Sans" w:hAnsi="Google Sans"/><w:color w:val="1f1f1f"/><w:shd w:fill="f0f4f9" w:val="clear"/><w:rtl w:val="0"/></w:rPr><w:t xml:space="preserve">[]; </w:t><w:br w:type="textWrapping"/><w:t xml:space="preserve">  };</w:t><w:br w:type="textWrapping"/><w:t xml:space="preserve">  </w:t><w:br w:type="textWrapping"/><w:t xml:space="preserve">  chat_log: </w:t></w:r><w:r w:rsidDel="00000000" w:rsidR="00000000" w:rsidRPr="00000000"><w:rPr><w:rFonts w:ascii="Google Sans" w:cs="Google Sans" w:eastAsia="Google Sans" w:hAnsi="Google Sans"/><w:i w:val="0"/><w:iCs w:val="0"/><w:color w:val="1967d2"/><w:sz w:val="20"/><w:szCs w:val="20"/><w:shd w:fill="f0f4f9" w:val="clear"/><w:rtl w:val="0"/></w:rPr><w:t xml:space="preserve">Array</w:t></w:r><w:r w:rsidDel="00000000" w:rsidR="00000000" w:rsidRPr="00000000"><w:rPr><w:rFonts w:ascii="Google Sans" w:cs="Google Sans" w:eastAsia="Google Sans" w:hAnsi="Google Sans"/><w:color w:val="1f1f1f"/><w:shd w:fill="f0f4f9" w:val="clear"/><w:rtl w:val="0"/></w:rPr><w:t xml:space="preserve">&lt;{</w:t><w:br w:type="textWrapping"/><w:t xml:space="preserve">    </w:t></w:r><w:r w:rsidDel="00000000" w:rsidR="00000000" w:rsidRPr="00000000"><w:rPr><w:rFonts w:ascii="Google Sans" w:cs="Google Sans" w:eastAsia="Google Sans" w:hAnsi="Google Sans"/><w:i w:val="0"/><w:iCs w:val="0"/><w:color w:val="b55908"/><w:sz w:val="20"/><w:szCs w:val="20"/><w:shd w:fill="f0f4f9" w:val="clear"/><w:rtl w:val="0"/></w:rPr><w:t xml:space="preserve">sender</w:t></w:r><w:r w:rsidDel="00000000" w:rsidR="00000000" w:rsidRPr="00000000"><w:rPr><w:rFonts w:ascii="Google Sans" w:cs="Google Sans" w:eastAsia="Google Sans" w:hAnsi="Google Sans"/><w:color w:val="1f1f1f"/><w:shd w:fill="f0f4f9" w:val="clear"/><w:rtl w:val="0"/></w:rPr><w:t xml:space="preserve">: </w:t></w:r><w:r w:rsidDel="00000000" w:rsidR="00000000" w:rsidRPr="00000000"><w:rPr><w:rFonts w:ascii="Google Sans" w:cs="Google Sans" w:eastAsia="Google Sans" w:hAnsi="Google Sans"/><w:i w:val="0"/><w:iCs w:val="0"/><w:color w:val="188038"/><w:sz w:val="20"/><w:szCs w:val="20"/><w:shd w:fill="f0f4f9" w:val="clear"/><w:rtl w:val="0"/></w:rPr><w:t xml:space="preserve">&quot;SYSTEM&quot;</w:t></w:r><w:r w:rsidDel="00000000" w:rsidR="00000000" w:rsidRPr="00000000"><w:rPr><w:rFonts w:ascii="Google Sans" w:cs="Google Sans" w:eastAsia="Google Sans" w:hAnsi="Google Sans"/><w:color w:val="1f1f1f"/><w:shd w:fill="f0f4f9" w:val="clear"/><w:rtl w:val="0"/></w:rPr><w:t xml:space="preserve"> | </w:t></w:r><w:r w:rsidDel="00000000" w:rsidR="00000000" w:rsidRPr="00000000"><w:rPr><w:rFonts w:ascii="Google Sans" w:cs="Google Sans" w:eastAsia="Google Sans" w:hAnsi="Google Sans"/><w:i w:val="0"/><w:iCs w:val="0"/><w:color w:val="188038"/><w:sz w:val="20"/><w:szCs w:val="20"/><w:shd w:fill="f0f4f9" w:val="clear"/><w:rtl w:val="0"/></w:rPr><w:t xml:space="preserve">&quot;AI_DIRECTOR&quot;</w:t></w:r><w:r w:rsidDel="00000000" w:rsidR="00000000" w:rsidRPr="00000000"><w:rPr><w:rFonts w:ascii="Google Sans" w:cs="Google Sans" w:eastAsia="Google Sans" w:hAnsi="Google Sans"/><w:color w:val="1f1f1f"/><w:shd w:fill="f0f4f9" w:val="clear"/><w:rtl w:val="0"/></w:rPr><w:t xml:space="preserve"> | </w:t></w:r><w:r w:rsidDel="00000000" w:rsidR="00000000" w:rsidRPr="00000000"><w:rPr><w:rFonts w:ascii="Google Sans" w:cs="Google Sans" w:eastAsia="Google Sans" w:hAnsi="Google Sans"/><w:i w:val="0"/><w:iCs w:val="0"/><w:color w:val="188038"/><w:sz w:val="20"/><w:szCs w:val="20"/><w:shd w:fill="f0f4f9" w:val="clear"/><w:rtl w:val="0"/></w:rPr><w:t xml:space="preserve">&quot;PLAYER&quot;</w:t></w:r><w:r w:rsidDel="00000000" w:rsidR="00000000" w:rsidRPr="00000000"><w:rPr><w:rFonts w:ascii="Google Sans" w:cs="Google Sans" w:eastAsia="Google Sans" w:hAnsi="Google Sans"/><w:color w:val="1f1f1f"/><w:shd w:fill="f0f4f9" w:val="clear"/><w:rtl w:val="0"/></w:rPr><w:t xml:space="preserve">;</w:t><w:br w:type="textWrapping"/><w:t xml:space="preserve">    text: </w:t></w:r><w:r w:rsidDel="00000000" w:rsidR="00000000" w:rsidRPr="00000000"><w:rPr><w:rFonts w:ascii="Google Sans" w:cs="Google Sans" w:eastAsia="Google Sans" w:hAnsi="Google Sans"/><w:i w:val="0"/><w:iCs w:val="0"/><w:color w:val="1967d2"/><w:sz w:val="20"/><w:szCs w:val="20"/><w:shd w:fill="f0f4f9" w:val="clear"/><w:rtl w:val="0"/></w:rPr><w:t xml:space="preserve">string</w:t></w:r><w:r w:rsidDel="00000000" w:rsidR="00000000" w:rsidRPr="00000000"><w:rPr><w:rFonts w:ascii="Google Sans" w:cs="Google Sans" w:eastAsia="Google Sans" w:hAnsi="Google Sans"/><w:color w:val="1f1f1f"/><w:shd w:fill="f0f4f9" w:val="clear"/><w:rtl w:val="0"/></w:rPr><w:t xml:space="preserve">;</w:t><w:br w:type="textWrapping"/><w:t xml:space="preserve">  }&gt;;</w:t><w:br w:type="textWrapping"/><w:t xml:space="preserve">}</w:t><w:br w:type="textWrapping"/></w:r></w:p><w:p w:rsidR="00000000" w:rsidDel="00000000" w:rsidP="00000000" w:rsidRDefault="00000000" w:rsidRPr="00000000" w14:paraId="00000022"><w:pPr><w:pStyle w:val="Heading3"/><w:pBdr><w:top w:space="0" w:sz="0" w:val="nil"/><w:left w:space="0" w:sz="0" w:val="nil"/><w:bottom w:space="0" w:sz="0" w:val="nil"/><w:right w:space="0" w:sz="0" w:val="nil"/><w:between w:space="0" w:sz="0" w:val="nil"/></w:pBdr><w:shd w:fill="auto" w:val="clear"/><w:spacing w:after="120" w:before="0" w:line="275.9999942779541" w:lineRule="auto"/><w:rPr><w:rFonts w:ascii="Google Sans" w:cs="Google Sans" w:eastAsia="Google Sans" w:hAnsi="Google Sans"/><w:color w:val="1f1f1f"/></w:rPr></w:pPr><w:r w:rsidDel="00000000" w:rsidR="00000000" w:rsidRPr="00000000"><w:rPr><w:rFonts w:ascii="Google Sans" w:cs="Google Sans" w:eastAsia="Google Sans" w:hAnsi="Google Sans"/><w:color w:val="1f1f1f"/><w:rtl w:val="0"/></w:rPr><w:t xml:space="preserve">How the Interaction Works (The Standard Cycle):</w:t></w:r></w:p><w:p w:rsidR="00000000" w:rsidDel="00000000" w:rsidP="00000000" w:rsidRDefault="00000000" w:rsidRPr="00000000" w14:paraId="00000023"><w:pPr><w:numPr><w:ilvl w:val="0"/><w:numId w:val="1"/></w:numPr><w:pBdr><w:top w:space="0" w:sz="0" w:val="nil"/><w:left w:space="0" w:sz="0" w:val="nil"/><w:bottom w:space="0" w:sz="0" w:val="nil"/><w:right w:space="0" w:sz="0" w:val="nil"/><w:between w:space="0" w:sz="0" w:val="nil"/></w:pBdr><w:shd w:fill="auto" w:val="clear"/><w:spacing w:after="0" w:afterAutospacing="0" w:line="275.9999942779541" w:lineRule="auto"/><w:ind w:left="480" w:hanging="360"/></w:pPr><w:r w:rsidDel="00000000" w:rsidR="00000000" w:rsidRPr="00000000"><w:rPr><w:rFonts w:ascii="Google Sans" w:cs="Google Sans" w:eastAsia="Google Sans" w:hAnsi="Google Sans"/><w:b w:val="1"/><w:bCs w:val="1"/><w:color w:val="1f1f1f"/><w:rtl w:val="0"/></w:rPr><w:t xml:space="preserve">You click the &quot;Assault&quot; button.</w:t></w:r></w:p><w:p w:rsidR="00000000" w:rsidDel="00000000" w:rsidP="00000000" w:rsidRDefault="00000000" w:rsidRPr="00000000" w14:paraId="00000024"><w:pPr><w:numPr><w:ilvl w:val="0"/><w:numId w:val="1"/></w:numPr><w:pBdr><w:top w:space="0" w:sz="0" w:val="nil"/><w:left w:space="0" w:sz="0" w:val="nil"/><w:bottom w:space="0" w:sz="0" w:val="nil"/><w:right w:space="0" w:sz="0" w:val="nil"/><w:between w:space="0" w:sz="0" w:val="nil"/></w:pBdr><w:shd w:fill="auto" w:val="clear"/><w:spacing w:after="0" w:afterAutospacing="0" w:before="0" w:beforeAutospacing="0" w:line="275.9999942779541" w:lineRule="auto"/><w:ind w:left="480" w:hanging="360"/></w:pPr><w:r w:rsidDel="00000000" w:rsidR="00000000" w:rsidRPr="00000000"><w:rPr><w:rFonts w:ascii="Google Sans" w:cs="Google Sans" w:eastAsia="Google Sans" w:hAnsi="Google Sans"/><w:color w:val="1f1f1f"/><w:rtl w:val="0"/></w:rPr><w:t xml:space="preserve">The UI does </w:t></w:r><w:r w:rsidDel="00000000" w:rsidR="00000000" w:rsidRPr="00000000"><w:rPr><w:rFonts w:ascii="Google Sans" w:cs="Google Sans" w:eastAsia="Google Sans" w:hAnsi="Google Sans"/><w:b w:val="1"/><w:bCs w:val="1"/><w:color w:val="1f1f1f"/><w:rtl w:val="0"/></w:rPr><w:t xml:space="preserve">not</w:t></w:r><w:r w:rsidDel="00000000" w:rsidR="00000000" w:rsidRPr="00000000"><w:rPr><w:rFonts w:ascii="Google Sans" w:cs="Google Sans" w:eastAsia="Google Sans" w:hAnsi="Google Sans"/><w:color w:val="1f1f1f"/><w:rtl w:val="0"/></w:rPr><w:t xml:space="preserve"> roll dice. It fires an event:</w:t></w:r><w:r w:rsidDel="00000000" w:rsidR="00000000" w:rsidRPr="00000000"><w:rPr><w:rFonts w:ascii="Arial" w:cs="Arial" w:eastAsia="Arial" w:hAnsi="Arial"/><w:b w:val="0"/><w:bCs w:val="0"/><w:i w:val="0"/><w:iCs w:val="0"/><w:smallCaps w:val="0"/><w:strike w:val="0"/><w:color w:val="000000"/><w:sz w:val="22"/><w:szCs w:val="22"/><w:u w:val="none"/><w:shd w:fill="auto" w:val="clear"/><w:vertAlign w:val="baseline"/><w:rtl w:val="0"/></w:rPr><w:br w:type="textWrapping"/></w:r><w:r w:rsidDel="00000000" w:rsidR="00000000" w:rsidRPr="00000000"><w:rPr><w:rFonts w:ascii="Google Sans" w:cs="Google Sans" w:eastAsia="Google Sans" w:hAnsi="Google Sans"/><w:color w:val="1f1f1f"/><w:rtl w:val="0"/></w:rPr><w:t xml:space="preserve">fetch('/api/action', { body: { action: &quot;ASSAULT&quot;, burn: 2, target: &quot;Wolf_01&quot; } })</w:t></w:r></w:p><w:p w:rsidR="00000000" w:rsidDel="00000000" w:rsidP="00000000" w:rsidRDefault="00000000" w:rsidRPr="00000000" w14:paraId="00000025"><w:pPr><w:numPr><w:ilvl w:val="0"/><w:numId w:val="1"/></w:numPr><w:pBdr><w:top w:space="0" w:sz="0" w:val="nil"/><w:left w:space="0" w:sz="0" w:val="nil"/><w:bottom w:space="0" w:sz="0" w:val="nil"/><w:right w:space="0" w:sz="0" w:val="nil"/><w:between w:space="0" w:sz="0" w:val="nil"/></w:pBdr><w:shd w:fill="auto" w:val="clear"/><w:spacing w:after="0" w:afterAutospacing="0" w:before="0" w:beforeAutospacing="0" w:line="275.9999942779541" w:lineRule="auto"/><w:ind w:left="480" w:hanging="360"/></w:pPr><w:r w:rsidDel="00000000" w:rsidR="00000000" w:rsidRPr="00000000"><w:rPr><w:rFonts w:ascii="Google Sans" w:cs="Google Sans" w:eastAsia="Google Sans" w:hAnsi="Google Sans"/><w:color w:val="1f1f1f"/><w:rtl w:val="0"/></w:rPr><w:t xml:space="preserve">The UI immediately sets ui_locked = true so you can't spam click.</w:t></w:r></w:p><w:p w:rsidR="00000000" w:rsidDel="00000000" w:rsidP="00000000" w:rsidRDefault="00000000" w:rsidRPr="00000000" w14:paraId="00000026"><w:pPr><w:numPr><w:ilvl w:val="0"/><w:numId w:val="1"/></w:numPr><w:pBdr><w:top w:space="0" w:sz="0" w:val="nil"/><w:left w:space="0" w:sz="0" w:val="nil"/><w:bottom w:space="0" w:sz="0" w:val="nil"/><w:right w:space="0" w:sz="0" w:val="nil"/><w:between w:space="0" w:sz="0" w:val="nil"/></w:pBdr><w:shd w:fill="auto" w:val="clear"/><w:spacing w:after="0" w:afterAutospacing="0" w:before="0" w:beforeAutospacing="0" w:line="275.9999942779541" w:lineRule="auto"/><w:ind w:left="480" w:hanging="360"/></w:pPr><w:r w:rsidDel="00000000" w:rsidR="00000000" w:rsidRPr="00000000"><w:rPr><w:rFonts w:ascii="Google Sans" w:cs="Google Sans" w:eastAsia="Google Sans" w:hAnsi="Google Sans"/><w:color w:val="1f1f1f"/><w:rtl w:val="0"/></w:rPr><w:t xml:space="preserve">Two seconds later, the backend replies with a fresh ClientGameState JSON object.</w:t></w:r></w:p><w:p w:rsidR="00000000" w:rsidDel="00000000" w:rsidP="00000000" w:rsidRDefault="00000000" w:rsidRPr="00000000" w14:paraId="00000027"><w:pPr><w:numPr><w:ilvl w:val="0"/><w:numId w:val="1"/></w:numPr><w:pBdr><w:top w:space="0" w:sz="0" w:val="nil"/><w:left w:space="0" w:sz="0" w:val="nil"/><w:bottom w:space="0" w:sz="0" w:val="nil"/><w:right w:space="0" w:sz="0" w:val="nil"/><w:between w:space="0" w:sz="0" w:val="nil"/></w:pBdr><w:shd w:fill="auto" w:val="clear"/><w:spacing w:after="120" w:before="0" w:beforeAutospacing="0" w:line="275.9999942779541" w:lineRule="auto"/><w:ind w:left="480" w:hanging="360"/></w:pPr><w:r w:rsidDel="00000000" w:rsidR="00000000" w:rsidRPr="00000000"><w:rPr><w:rFonts w:ascii="Google Sans" w:cs="Google Sans" w:eastAsia="Google Sans" w:hAnsi="Google Sans"/><w:color w:val="1f1f1f"/><w:rtl w:val="0"/></w:rPr><w:t xml:space="preserve">React receives the JSON, updates the Stamina bar (which visually drops down), adds the AI's story to the chat_log, and unlocks the UI.</w:t></w:r></w:p><w:p w:rsidR="00000000" w:rsidDel="00000000" w:rsidP="00000000" w:rsidRDefault="00000000" w:rsidRPr="00000000" w14:paraId="00000028"><w:pPr><w:pBdr><w:top w:space="0" w:sz="0" w:val="nil"/><w:left w:space="0" w:sz="0" w:val="nil"/><w:bottom w:space="0" w:sz="0" w:val="nil"/><w:right w:space="0" w:sz="0" w:val="nil"/><w:between w:space="0" w:sz="0" w:val="nil"/></w:pBdr><w:shd w:fill="auto" w:val="clear"/><w:spacing w:after="240" w:before="120" w:line="275.9999942779541" w:lineRule="auto"/><w:rPr><w:rFonts w:ascii="Google Sans" w:cs="Google Sans" w:eastAsia="Google Sans" w:hAnsi="Google Sans"/><w:color w:val="1f1f1f"/></w:rPr></w:pPr><w:r w:rsidDel="00000000" w:rsidR="00000000" w:rsidRPr="00000000"><w:pict><v:rect style="width:0.0pt;height:1.5pt" o:hr="t" o:hrstd="t" o:hralign="center" fillcolor="#A0A0A0" stroked="f"/></w:pict></w:r><w:r w:rsidDel="00000000" w:rsidR="00000000" w:rsidRPr="00000000"><w:rPr><w:rFonts w:ascii="Google Sans" w:cs="Google Sans" w:eastAsia="Google Sans" w:hAnsi="Google Sans"/><w:color w:val="1f1f1f"/><w:rtl w:val="0"/></w:rPr><w:t xml:space="preserve">This React foundation perfectly isolates your front-end. You can spend weeks making the CSS look incredible, wiring up the PixiJS MapCanvas to render your 2D tiles, and building the Bio-Matrix slider without ever worrying about the backend Python math.</w:t></w:r></w:p><w:p w:rsidR="00000000" w:rsidDel="00000000" w:rsidP="00000000" w:rsidRDefault="00000000" w:rsidRPr="00000000" w14:paraId="00000029"><w:pPr><w:pBdr><w:top w:space="0" w:sz="0" w:val="nil"/><w:left w:space="0" w:sz="0" w:val="nil"/><w:bottom w:space="0" w:sz="0" w:val="nil"/><w:right w:space="0" w:sz="0" w:val="nil"/><w:between w:space="0" w:sz="0" w:val="nil"/></w:pBdr><w:shd w:fill="auto" w:val="clear"/><w:spacing w:after="240" w:line="275.9999942779541" w:lineRule="auto"/><w:rPr><w:rFonts w:ascii="Google Sans" w:cs="Google Sans" w:eastAsia="Google Sans" w:hAnsi="Google Sans"/><w:color w:val="1f1f1f"/></w:rPr></w:pPr><w:r w:rsidDel="00000000" w:rsidR="00000000" w:rsidRPr="00000000"><w:rPr><w:rFonts w:ascii="Google Sans" w:cs="Google Sans" w:eastAsia="Google Sans" w:hAnsi="Google Sans"/><w:color w:val="1f1f1f"/><w:rtl w:val="0"/></w:rPr><w:t xml:space="preserve">Does this clean, pure-frontend React architecture give you the exact starting point you need to build the player view?</w:t></w:r></w:p><w:sectPr><w:pgSz w:h="15840" w:w="12240" w:orient="portrait"/><w:pgMar w:bottom="1440" w:top="1440" w:left="1440" w:right="1440" w:header="0" w:footer="720"/><w:pgNumType w:start="1"/></w:sectPr></w:body></w:document>